Workbook

Sheet Performance Testing Info
A1: Workstream | B1: Performance Testing (Yes/No) | C1: If no, why? | D1: Total Scenarios | E1: Total Functional Steps | F1: Total Excluding N/A | G1: Plan to Week | H1: Planned Executed Scenarios | I1: Actual Passed Scenarios | J1: Planned Remaining | K1: Plan Week % Complete | L1: Total Remaining | M1: Execution % | N1: Pass Rate % | O1: Business KPI | P1: Performance Requirements | Q1: How load is determined
A2: Architecture (UCDP) | B2: yes | C2: yes | D2: 6 | E2: 50 | F2: 6 | G2: 6 | H2: 6 | I2: 6 | J2: =G2-H2 -> 0 | K2: =H2/G2*100 -> 100 | L2: =D2-H2 -> 0 | M2: =H2/D2*100 -> 100 | N2: =I2/H2*100 -> 100 | O2: - Realtime ingestion of interactions from the channels - Sub-second interactions retrievals | P2: - System should be capable of handling 1 million reads & 1 million writes in parallel for a duration of 1 hour - System should not be exceeding response times of 100ms under peak-load scenarios | Q2: - Did volume analysis of existing CCINs for NW + Legacy customers, which came to ~300 million interactions in a month - Understood from business the peak load scenarios - Multiplied the peak load scenario number by 10x to achieve a much higher throughput - Stress tested the system with near maximum concurrency to come to a point where the system starts to throttle
A3: Case Management | B3: yes | C3: yes | D3: =COUNTA('Case Management'!B3:B86) -> 9 | E3: 36 | F3: 6 | G3: 6 | H3: 6 | I3: 6 | J3: =G3-H3 -> 0 | K3: =H3/G3*100 -> 100 | L3: =D3-H3 -> 3 | M3: =H3/D3*100 -> 66.666667 | N3: =I3/H3*100 -> 100 | O3: Average Response time,90% Line, % errors | P3: API's should not be exceeding 5 sec under peak load scenarios | Q3: volume details understood from business peak load scenarios it is around ~300 so 10x to achieve transactions per hour
A4: CS Field Service | B4: yes | C4: yes | D4: =COUNTA('CS Field Service'!B3:B58) -> 8 | E4: 29 | F4: 5 | G4: 5 | H4: 5 | I4: 5 | J4: =G4-H4 -> 0 | K4: =H4/G4*100 -> 100 | L4: =D4-H4 -> 3 | M4: =H4/D4*100 -> 62.5 | N4: =I4/H4*100 -> 100 | O4: Average Response time,90% Line, % errors | P4: API's should not be exceeding 5 sec under peak load scenarios | Q4: volume details understood from business peak load scenarios it is around ~9 so 10x to achieve transactions per hour, Discussed with Business(Urquiaga, Alejandro), @Steven Licari provided load details and we used the same multiplied by 10X
A5: Employee Desktop | B5: yes | C5: yes | D5: 9 | E5: 72 | F5: 9 | G5: 9 | H5: 9 | I5: 9 | J5: =G5-H5 -> 0 | K5: =H5/G5*100 -> 100 | L5: =D5-H5 -> 0 | M5: =H5/D5*100 -> 100 | N5: =I5/H5*100 -> 100 | O5: Average Response time,90% Line, % errors | P5: API's should not be exceeding 5 sec under peak load scenarios | Q5: volume details understood from business peak load scenarios it is around ~1000 so 10x to achieve transactions per hour, Discussed with Business Castro, Jaime, & Vargas, Ricardo, with provided load details and we used the same multiplied by 10X
A6: Integrations & Mulesoft | B6: yes | C6: yes | D6: =COUNTA('Integrations Mulesfot'!A3:A106) -> 5 | E6: 16 | F6: 5 | G6: 5 | H6: 5 | I6: 5 | J6: =G6-H6 -> 0 | K6: =H6/G6*100 -> 100 | L6: =D6-H6 -> 0 | M6: =H6/D6*100 -> 100 | N6: =I6/H6*100 -> 100 | O6: Average Response time,90% Line, % errors | P6: On an average, it should not take more than 5 Sec | Q6: Determined from Unified CRM scenarios
A7: Web Optimization & Mobile | B7: yes | C7: yes | D7: =COUNTA('Web Optimization & Mobile'!B3:B84) -> 8 | E7: 11 | F7: 4 | G7: 4 | H7: 4 | I7: 4 | J7: =G7-H7 -> 0 | K7: =H7/G7*100 -> 100 | L7: =D7-H7 -> 4 | M7: =H7/D7*100 -> 50 | N7: =I7/H7*100 -> 100 | O7: Average Respnse time,90% Line, % errors | P7: 90% of calls should not exceed 3 sec under peak load, target <5% errors | Q7: Max traffic seen on site for Legacy + NW customers according to Adobe Analytics + 10% accounting for growth
A8: Total | D8: =SUM(D2:D7) -> 45 | E8: =SUM(E2:E7) -> 214 | F8: =SUM(F2:F7) -> 35 | G8: =SUM(G2:G7) -> 35 | H8: =SUM(H2:H7) -> 35 | I8: =SUM(I2:I7) -> 35 | J8: =G8-H8 -> 0 | K8: =H8/G8*100 -> 100 | L8: =D8-H8 -> 10 | M8: =H8/D8*100 -> 77.777778 | N8: =I8/H8*100 -> 100
A12: Planned By Week
A13: Workstream | D13: Week 1 (03/10/2025-03/14/2025) | E13: Week 2 (03/17/2025-03/21/2025) | F13: Week 3 (03/24/2025-03/28/2025) | G13: Week 4 (03/31/2025-04/04/2025) | H13: Week 5 (04/07/2025-04/10/2025) | I13: Total
A14: Architecture (UCDP) | D14: 6 | I14: =SUM(D14:H14) -> 6
A15: Case Management | E15: 6 | I15: =SUM(D15:H15) -> 6
A16: CS Field Service | G16: 3 | H16: 2 | I16: =SUM(D16:H16) -> 5
A17: Employee Desktop | G17: 7 | H17: 2 | I17: =SUM(D17:H17) -> 9
A18: Integrations & Mulesoft | D18: 5 | I18: =SUM(D18:H18) -> 5
A19: Telephony | I19: =SUM(D19:H19) -> 0
A20: Web Optimization & Mobile | G20: 1 | H20: 3 | I20: =SUM(D20:H20) -> 4
A21: Total | D21: =SUM(D14:D20) -> 11 | E21: =SUM(E14:E20) -> 6 | F21: =SUM(F14:F20) -> 0 | G21: =SUM(G14:G20) -> 11 | H21: =SUM(H14:H20) -> 7 | I21: =SUM(D21:H21) -> 35
A23: Workstream | B23: Total Scenarios | C23: Plan to Week | D23: Planned Executed Scenarios | E23: Actual Passed Scenarios | F23: Planned Remaining | G23: Plan Week % Complete | H23: Total Remaining | I23: Execution % | J23: Pass Rate % | K23: Business KPI | L23: Performance Requirements | M23: How load is determined
A24: Convo AI | B24: 8
A25: Telephony | B25: 4
A28: Workstream | D28: Performance Testing (Yes/No) | E28: Performance Testing (Yes/No) | F28: If no, why? | G28: Point of Contact | H28: Number of Scenarios for Performance Testing | I28: Total Functional Steps
A29: Architecture (UCDP) | D29: yes | E29: yes | F29: yes | G29: Hussain Gilani/ Tisha Haque | H29: =COUNTA('Architecture (UCDP)'!A78:A176) -> 0 | I29: 50
A30: Case Management | D30: yes | E30: yes | F30: yes | G30: Srividya Chamarthy | H30: =COUNTA('Case Management'!B26:B119) -> 7 | I30: 36
A31: Convo AI (IVR) | D31: yes | E31: yes | F31: yes | G31: Vishwanath Vinnakota | H31: 8 | I31: =COUNTA('Convo AI (IVR)'!B131:B228) -> 42
A32: CS Field Service | D32: yes | E32: yes | F32: yes | G32: Srividya Chamarthy | H32: =COUNTA('CS Field Service'!B29:B94) -> 11 | I32: =COUNTA('CS Field Service'!C29:C94) -> 39
A33: DCP Customer communications | D33: No | E33: No | F33: Not part of IR1.0 | G33: No | H33: N/A | I33: N/A
A34: Employee Desktop | D34: yes | E34: yes | F34: yes | G34: Srividya Chamarthy | H34: =COUNTA('Employee Desktop'!B33:B126) -> 13 | I34: =COUNTA('Employee Desktop'!C33:C127) -> 68
A35: Integrations & Mulesoft | D35: yes | E35: yes | F35: yes | G35: Ramesh Reddy Kota | H35: 5 | I35: =COUNTA('Integrations Mulesfot'!B35:B139) -> 0
A36: Reporting & Analytics | D36: No | E36: No | F36: Only 9 test cases and nothing for performance test | G36: No | H36: N/A | I36: N/A
A37: SAP - Billing & Payment (BPO) | D37: No | E37: N/A | F37: No changes in IR1 that require performance testing. Some are planned for later releases | G37: N/A | H37: N/A | I37: N/A
A38: SAP - Revenue Recovery | D38: N/A | E38: N/A | F38: N/A | G38: N/A | H38: N/A | I38: N/A
A39: SAP - Basis | D39: No | E39: No | F39: Only offcycle performance test to validate solution for DEE | G39: No | H39: N/A | I39: N/A
A40: SAP- Tax | D40: No | E40: No | F40: Waiting to install Vertex. Not available for IR 1.0 | G40: No | H40: N/A | I40: N/A
A41: Telephony | D41: yes | E41: yes | F41: yes | G41: Vishwanath Vinnakota | H41: 4 | I41: 27
A42: Web Optimization & Mobile | D42: yes | E42: yes | F42: yes | G42: Saswat Ranjan Sahoo | H42: =COUNTA(Telephony!A37:A153) -> 0 | I42: =COUNTA(Telephony!B37:B126) -> 0
A50: Workstream | B50: POC
A51: Architecture (UCDP) | B51: Tisha Haque Manish Vastrakar
A52: Convo AI | B52: Gajendran Karthikeyan
A53: Case Management | B53: Sravya Polavarapu, Sunanda Poda, Srividhya Chamarthy
A54: CS Field Service | B54: Sravya Polavarapu, Sunanda Poda, Srividhya Chamarthy
A55: Integrations & Mulesoft | B55: Sudhirkumar Kuna, Srinivasu Koka
A56: Employee Desktop | B56: Sravya Polavarapu, Sunanda Poda, Srividhya Chamarthy
A57: Web Optimization & Mobile | B57: Saswat Ranjan Sahoo

Sheet Architecture (UCDP)
K1: Legacy Standard | O1: FPL NW Standard | S1: Industry Standard
A2: Performance Testing Scenarios | B2: Functional Steps | C2: Time Interval | D2: # Transactions | E2: Average Response Time | F2: 90% Line | G2: Planned Execution Date | H2: Execution Status | I2: Performance Test Lead | J2: Results | K2: Legacy Application | L2: User/Data Load Volumetrics | M2: Average Response Time | N2: 90% Line | O2: FPL NW Application | P2: User/Data Load Volumetrics | Q2: Average Response Time | R2: 90% Line | S2: Average Response Time | T2: 90% Line | U2: Reasons for Deviations | V2: How 90% Line is calculated for Current Performance Test
A3: Write 100K records at 70 TPS into UCDP and determine key metrics at every 10 min interval which include, Test duration, Avg response time, Min response TIme, 90th/95th and 99th percentile response time, Error %, Throughput, Avg recieved and sent, Total consumed WCUs, Storage used and Total cost ( WCU + Storage) | B3: - Generate mock data using Faker library - Ensure AWS perf test env readiness - Setup JMeter, import test data and execute perf test script - Take snapshots at preset intervals to capture key performance metrics from JMeter - Capture usage and cost metrics from AWS | C3: 10 mins | D3: 30429 | E3: 24 ms | F3: 47 ms | G3: 45706 | H3: Passed | I3: Tisha Haque Manish Vastrakar | J3: UCDP PerformanceAnalysis(100K_70TPS)_18022025.docx | K3: UCDP is a greenfield system. No legacy Application or standards | O3: UCDP is a greenfield system. No NW application or Standard
C4: 20 mins | D4: 77308 | E4: 27 ms | F4: 47 ms
C5: 25 mins | D5: 100000 | E5: 28 ms | F5: 49 ms
A6: Write 200k records at 70 TPS into UCDP and determine key metrics which include, Test duration, Avg response time, Min response TIme, 90th/95th and 99th percentile response time, Error %, Throughput, Avg recieved and sent, Total consumed WCUs, Storage used and Total cost ( WCU + Storage) | B6: - Generate mock data using Faker library - Ensure AWS perf test env readiness - Setup JMeter, import test data and execute perf test script - Take snapshots at preset intervals to capture key performance metrics from JMeter - Capture usage and cost metrics from AWS | C6: 10 mins | D6: 42670 | E6: 18 ms | F6: 29 ms | G6: 45346 | H6: Passed | I6: Tisha Haque Manish Vastrakar | J6: UCDP PerformanceAnalysis(200K_70TPS)_20022025.docx
C7: 20 mins | D7: 85943 | E7: 19 ms | F7: 32 ms
C8: 30 mins | D8: 128358 | E8: 19 ms | F8: 31 ms
C9: 40 mins | D9: 171181 | E9: 19 ms | F9: 32 ms
C10: 46 mins | D10: 200000 | E10: 19 ms | F10: 32 ms
A11: Write 1M records at 70 TPS into UCDP and determine key metrics which include, Test duration, Avg response time, Min response TIme, 90th/95th and 99th percentile response time, Error %, Throughput, Avg recieved and sent, Total consumed WCUs, Storage used and Total cost ( WCU + Storage) | B11: - Generate mock data using Faker library - Ensure AWS perf test env readiness - Setup JMeter, import test data and execute perf test script - Take snapshots at preset intervals to capture key performance metrics from JMeter - Capture usage and cost metrics from AWS | C11: 15 mins | D11: 64029 | E11: 18 ms | F11: 26 ms | G11: 45346 | H11: Passed | I11: Tisha Haque Manish Vastrakar | J11: UCDP PerformanceAnalysis(1M_70TPS)_24022025.docx
C12: 30 mins | D12: 128324 | E12: 18 ms | F12: 25 ms
C13: 45 mins | D13: 193210 | E13: 18 ms | F13: 26 ms
C14: 60 mins | D14: 256912 | E14: 18 ms | F14: 26 ms
C15: 75 mins | D15: 321199 | E15: 18 ms | F15: 26 ms
C16: 90 mins | D16: 385462 | E16: 18 ms | F16: 27 ms
C17: 105 mins | D17: 449734 | E17: 18 ms | F17: 27 ms
C18: 120 mins | D18: 514011 | E18: 18 ms | F18: 27 ms
C19: 135 mins | D19: 578277 | E19: 18 ms | F19: 27 ms
C20: 150 mins | D20: 642575 | E20: 18 ms | F20: 27 ms
C21: 165 mins | D21: 706877 | E21: 18 ms | F21: 27ms
C22: 180 mins | D22: 771138 | E22: 18 ms | F22: 27 ms
C23: 195 mins | D23: 835495 | E23: 18 ms | F23: 27 ms
... C26: 233 mins | D26: 1000000 | E26: 17 ms | F26: 26 ms
A27: Write 1M records at 130 TPS into UCDP and determine key metrics which include, Test duration, Avg response time, Min response TIme, 90th/95th and 99th percentile response time, Error %, Throughput, Avg recieved and sent, Total consumed WCUs, Storage used and Total cost ( WCU + Storage) | B27: - Generate mock data using Faker library - Ensure AWS perf test env readiness - Setup JMeter, import test data and execute perf test script - Take snapshots at preset intervals to capture key performance metrics from JMeter - Capture usage and cost metrics from AWS | C27: 20 mins | D27: 155582 | E27: 19 ms | F27: 24 ms | G27: 45719 | H27: Passed | I27: Tisha Haque Manish Vastrakar | J27: UCDP PerformanceAnalysis(1M_130TPS)_26022025.docx
C28: 40 mins | D28: 311542 | E28: 18 ms | F28: 23 ms
C29: 60 mins | D29: 467666 | E29: 19 ms | F29: 24 ms
C30: 80 mins | D30: 623908 | E30: 18 ms | F30: 24 ms
C31: 100 mins | D31: 780775 | E31: 18 ms | F31: 23 ms
C32: 120 mins | D32: 935861 | E32: 18 ms | F32: 23 ms
C33: 128 mins | D33: 1000000 | E33: 18 ms | F33: 23 ms
A34: Simultanious 1M record read at 130 TPS from UCDP and 1M record write at 130 TPS into UCDP and determine key metrics which include, Test duration, Avg response time, Min response TIme, 90th/95th and 99th percentile response time, Error %, Throughput, Avg recieved and sent, Total consumed WCUs, Storage used and Total cost ( WCU + Storage) | B34: - Generate mock data using Faker library - Ensure AWS perf test env readiness - Setup JMeter, import test data and execute perf test script - Take snapshots at preset intervals to capture key performance metrics from JMeter - Capture usage and cost metrics from AWS | C34: 20 mins | D34: 155557 (Write) | E34: 18 ms | F34: 23 ms | G34: 45719 | H34: Passed | I34: Tisha Haque Manish Vastrakar | J34: UCDP PerformanceAnalysis(1M_READ_130TPS_1M_WRITE_130TPS)_03032025.docx
C35: 40 mins | D35: 311674 (Write) | E35: 18 ms | F35: 23 ms
D36: 117000 (Read) | E36: 17 ms | F36: 22 ms
C37: 60 mins | D37: 467552 (Write) | E37: 18 ms | F37: 23 ms
D38: 272882 (Read) | E38: 17 ms | F38: 22 ms
C39: 80 mins | D39: 623728 (Write) | E39: 18 ms | F39: 23 ms
D40: 429055 (Read) | E40: 17 ms | F40: 22 ms
C41: 100 mins | D41: 779810 (Write) | E41: 18 ms | F41: 23 ms
D42: 585139 (Read) | E42: 17 ms | F42: 23 ms
C43: 120 mins | D43: 935792 (Write) | E43: 18 ms | F43: 23 ms
D44: 741117 (Read) | E44: 17 ms | F44: 23 ms
C45: 140 mins | D45: 1000000 (Write) | E45: 18 ms | F45: 24 ms
D46: 897054 (Read) | E46: 17 ms | F46: 22 ms
C47: 153 mins | D47: 1000000 (Write) | E47: 18 ms | F47: 24 ms
D48: 1000000 (Read) | E48: 17 ms | F48: 22 ms
A49: Simultanious 1M record read at 260 TPS from UCDP and 1M record write at 260 TPS into UCDP and determine key metrics which include, Test duration, Avg response time, Min response TIme, 90th/95th and 99th percentile response time, Error %, Throughput, Avg recieved and sent, Total consumed WCUs, Storage used and Total cost ( WCU + Storage) | B49: - Generate mock data using Faker library - Ensure AWS perf test env readiness - Setup JMeter, import test data and execute perf test script - Take snapshots at preset intervals to capture key performance metrics from JMeter - Capture usage and cost metrics from AWS | C49: 10 mins | D49: 152134 (Write) | E49: 38 ms | F49: 62 ms | G49: 45721 | H49: Passed | I49: Tisha Haque Manish Vastrakar | J49: UCDP PerformanceAnalysis(1M_READ_260TPS_1M_WRITE_260TPS)_05032025.docx
D50: 155163 (Read) | E50: 17 ms | F50: 22 ms
C51: 20 mins | D51: 309433 (Write) | E51: 35 ms | F51: 58 ms
D52: 310835 (Read) | E52: 17 ms | F52: 22 ms
C53: 30 mins | D53: 465022 (Write) | E53: 33 ms | F53: 54 ms
D54: 466963 (Read) | E54: 17 ms | F54: 22 ms
C55: 40 mins | D55: 621117 (Write) | E55: 32 ms | F55: 52 ms
D56: 622773 (Read) | E56: 17 ms | F56: 22 ms
C57: 50 mins | D57: 777279 (Write) | E57: 31 ms | F57: 50 ms
D58: 778981 (Read) | E58: 17 ms | F58: 22 ms
C59: 60 mins | D59: 933234 (Write) | E59: 31 ms | F59: 49 ms
D60: 934850 (Read) | E60: 17 ms | F60: 22 ms
C61: 64 mins | D61: 1000000 (Write) | E61: 31 ms | F61: 49 ms
D62: 1000000 (Read) | E62: 17 ms | F62: 22 ms

Sheet Convo AI (IVR)
F1: Execution #1 | L1: Execution #2 | X1: Legacy Standard | AB1: FPL NW Standard | AF1: Industry Standard
A2: Performance Testing Scenarios | B2: Functional Steps | C2: Phone no in SIT | D2: Hammer Step Label | E2: Performance Test Lead | F2: Planned Execution Date 1st Round | G2: Execution Status | H2: No.of requests | I2: Average (sec) | J2: 90th Percentile (sec) | K2: Confluence Link | L2: Planned Execution Date 2nd Round | M2: Execution Status | N2: No.of requests | O2: Average (sec) | P2: 90th Percentile (sec) | Q2: Confluence Link | R2: Planned Execution Date 3rd Round | S2: Execution Status | T2: No.of requests | U2: Avg response time(ms) | V2: 90%Line (ms) | W2: Test Cases | X2: Legacy Application | Y2: User/Data Load Volumetrics | Z2: Average Response Time | AA2: 90% Line | AB2: FPL NW Application | AC2: User/Data Load Volumetrics | AD2: Average Response Time | AE2: 90% Line | AF2: Average Response Time | AG2: 90% Line | AH2: Reasons for Deviations | AI2: How 90% Line is calculated for Current Performance Test
A3: Report Outage No ANI match | B3: Dial the FPL customer service number and the system greets with the welcome message | C3: FPL customer service No | D3: Place Call | F3: 45813 | G3: Passed | K3: https://confluence.nexteraenergy.com/x/S0buJQ | L3: 45830 | M3: Passed | N3: 97829 | O3: 2.91 | P3: 16.4894 | Q3: https://confluence.nexteraenergy.com/x/S0buJQ
B4: System prompts an emergency message | D4: Recognize Greeting | O4: 1.04 | P4: 1.3619
B5: System play HVCA No ANI | D5: Recognize Emergency Message | O5: 2.65 | P5: 3.6096
B6: Customer prompts the Report an Outage from the limited options | C6: {Report Outage} | D6: Recognize Please Wait | O6: 0.5 | P6: 1.0604
B7: Customer prompts "Yes" | C7: {Yes} | D7: Recognize Outage Menu | O7: 0.35 | P7: 4.0592
B8: Customer provided account number | C8: Account Number | D8: Say 1
B9: Wait message | D9: Recognize Acct or Phone Number | O9: 1.53 | P9: 2.1529
B10: Customer provided account number | D10: Say 2
C11: {Yes} | D11: Recognize Enter Acct Number | O11: 1.41 | P11: 2.0984
D12: Press 2
D13: Recognize Wait Message | O13: 3.97 | P13: 6.0854
B14: System Prompts | D14: Recognize Service Address | O14: 1.31 | P14: 10.5949
B15: Customer ends the call | D15: Say 3
D16: Recognize Completely without power | O16: 2.93
D17: Say 4
D18: Recognize Creating Outage Report | O18: 1.43 | P18: 2.4487
D19: Recognize Callback | O19: 5.96 | P19: 6.374
D20: Say
D21: Recognize Submitted your report | O21: 3.26 | P21: 8.0895
D22: Recognize Restoration Estimate | O22: 0.39 | P22: 0.806
D23: Release Call
A24: Report Outage ANI match | B24: Dial the FPL customer service number. | C24: FPL customer service No | D24: Place Call | F24: 45813 | G24: Passed | K24: https://confluence.nexteraenergy.com/x/S0buJQ | L24: 45830 | M24: Passed | N24: 67434 | O24: 2.91 | P24: 16.4894 | Q24: https://confluence.nexteraenergy.com/x/S0buJQ
B25: System prompts emergency alert message | D25: Recognize Greeting | O25: 1.04 | P25: 1.3619
B26: Wait message | D26: Recognize Emergency Message | O26: 2.65 | P26: 3.6096
B27: System waits for a while and prompts | D27: Recognize Please Wait | O27: 0.5 | P27: 1.0604
D28: Recognize Located Account | O28: 0.09 | P28: 3.865
B29: Customer prompts as "Yes" | C29: {yes} | D29: Recognize Service Address | O29: 1.31 | P29: 10.5949
B30: Customer prompts as "yes, power outage in our house" | C30: {yes} | D30: Say 1
D31: Recognize Calling to Report an Outage | O31: 2.35 | P31: 5.9602
B32: Customer prompts as "ok" | C32: {yes} | D32: Say 2
C33: {ok} | D33: Recognize Completely Without Power | O33: 2.93
D34: Say 3
B35: System Prompts | D35: Recognize Creating Outage Report | O35: 1.43 | P35: 2.4487
B36: Customer ends the call | D36: Recognize Contact you on this number | O36: 5.92 | P36: 6.3721
D37: Say
D38: Recognize Submitted your report | O38: 3.26 | P38: 8.0895
D39: Recognize Restoration Estimate | O39: 0.39 | P39: 0.806
D40: Wait
D41: Release Call
A42: Police/Fire | B42: Police/Fire/Publix dials outage toll free number (NW + Legacy Number): 833-919-0943. Tester to call from a phone number which is not present in the FPL database and results in No ANI Match | C42: Outage toll free number(NW + Legacy Number): 833-919-0943 | D42: Place Call | F42: 45813 | G42: Passed | H42: 2180 | K42: https://confluence.nexteraenergy.com/x/S0buJQ | L42: 45830 | M42: Passed | N42: 804 | O42: 2.91 | P42: 16.4894 | Q42: https://confluence.nexteraenergy.com/x/S0buJQ
B43: IVR Wait prompt | D43: Recognize Greeting | I43: 1.18 | O43: 1.04 | P43: 1.3619
B44: IVR plays prompt to caller | C44: {711} or {777} | D44: Recognize Emergency Message | I44: 2.34 | O44: 2.65 | P44: 3.6096
B45: Caller enters PIN (777 or 711) | D45: Recognize Please Wait | I45: 0.6 | O45: 0.5 | P45: 1.0604
D46: Recognize Menu | I46: 2.19 | O46: 0.35 | P46: 1.514
D47: Press
D48: Recognize Transfer to Agents | I48: 2.55 | O48: 1.65 | P48: 2.0225
D49: Release Call
A50: Outage Update No ANI Match | B50: Dial the FPL customer service number | C50: FPL customer service No | D50: Place Call | F50: 45813 | G50: Passed | H50: 6014 | K50: https://confluence.nexteraenergy.com/x/S0buJQ | L50: 45830 | M50: Passed | N50: 69773 | O50: 2.91 | P50: 16.4894 | Q50: https://confluence.nexteraenergy.com/x/S0buJQ
B51: System prompt Emergency situation message | D51: Recognize Greeting | G51: Passed | I51: 1.18 | L51: 45813 | M51: Passed | O51: 1.04 | P51: 1.3619
B52: System play HVCA No ANI | D52: Recognize Emergency Message | G52: Passed | I52: 2.34 | L52: 45813 | M52: Passed | O52: 2.65 | P52: 3.6096
B53: Customer prompts the Report an Outage from the limited options | C53: {Outage Update} | D53: Recognize Please Wait | G53: Passed | I53: 0.6 | L53: 45813 | M53: Passed | O53: 0.5 | P53: 1.0604
B54: Customer prompts "Yes" | C54: {Yes} | D54: Recognize Outage Menu | G54: Passed | I54: 2.16 | L54: 45813 | M54: Passed | O54: 0.35 | P54: 4.0592
B55: Customer provided account number | C55: {Account number} 7126746168 | D55: Press 1 | G55: Passed | L55: 45813 | M55: Passed
B56: Wait message | D56: Recognize Acct or Phone Number | G56: Passed | I56: 1.68 | L56: 45813 | M56: Passed | O56: 1.53 | P56: 2.1529
B57: customer provided account number | D57: Say | G57: Passed | L57: 45813 | M57: Passed
B58: System prompt if the customer is reaching out for an outage update | C58: {Yes} | D58: Recognize Enter Acct Number | G58: Passed | I58: 1.34 | L58: 45813 | M58: Passed | O58: 1.41 | P58: 2.0984
B59: Syetm plays message about Outage | C59: {Yes} | D59: Press 3 | G59: Passed | L59: 45813 | M59: Passed
B60: System prompt ETR message | D60: Recognize Wait Message | G60: Passed | I60: 3.95 | L60: 45813 | M60: Passed | O60: 3.97 | P60: 6.0854
B61: Customer say Ok | D61: Recognize Service Address | G61: Passed | I61: 2.38 | L61: 45813 | M61: Passed | O61: 1.31 | P61: 10.5949
B62: System shares ticket number | D62: Say 2 | G62: Passed | L62: 45813 | M62: Passed
B63: With HVCA mode as ON, system will provide an end message | D63: Recognize Difficulty without power | G63: Passed | I63: 3.02 | L63: 45813 | M63: Passed | O63: 3.24 | P63: 6.0992
B64: Customer end the call | D64: Recognize Latest Update | G64: Passed | I64: 0.97 | L64: 45813 | M64: Passed | O64: 0.03 | P64: 0.2165
D65: Recognize Outage Update | I65: 1.07 | O65: 0.45 | P65: 0.9754
D66: Wait
D67: Release Call
A68: Outage Update with ANI Match | B68: Dial the FPL customer service number | C68: FPL customer service No | D68: Place Call | F68: 45813 | G68: Passed | H68: 6014 | K68: https://confluence.nexteraenergy.com/x/S0buJQ | L68: 45830 | M68: Passed | N68: 44664 | O68: 2.91 | P68: 16.4894 | Q68: https://confluence.nexteraenergy.com/x/S0buJQ
B69: System prompt Emergency situation message | D69: Recognize Greeting | I69: 1.18 | L69: 45830 | M69: Passed | O69: 1.04 | P69: 1.3619
B70: Wait messgae | D70: Recognize Emergency Message | I70: 2.34 | L70: 45830 | M70: Passed | O70: 2.65 | P70: 3.6096
B71: System prompt as phone number located | D71: Recognize Please Wait | I71: 0.6 | L71: 45830 | M71: Passed | O71: 0.5 | P71: 1.0604
B72: System prompt for confirm service address | D72: Recognize Located Account | I72: 2.27 | L72: 45830 | M72: Passed | O72: 0.09 | P72: 3.865
B73: System prompt if the customer is reaching out for an outage update | C73: {Yes} | D73: Recognize Service Address | I73: 2.38 | L73: 45830 | M73: Passed | O73: 1.31 | P73: 10.5949
B74: Syetm plays message about Outage | C74: {Yes} | D74: Say 1 | L74: 45830 | M74: Passed
B75: System prompt ETR message | D75: Recognize Calling for an Outage Update | I75: 4.25 | L75: 45830 | M75: Passed | O75: 2.38 | P75: 5.857
B76: Customer say Ok | D76: Say 2 | L76: 45830 | M76: Passed
B77: System shares ticket number | D77: Recognize Difficulty without power | I77: 3.02 | L77: 45830 | M77: Passed | O77: 3.24 | P77: 6.0992
B78: With HVCA mode as ON, system will provide an end message | D78: Recognize Latest Update | I78: 0.97 | L78: 45830 | M78: Passed | O78: 0.03 | P78: 0.2165
B79: Customer end the call | C79: {disconnect Call} | D79: Recognize Timing | L79: 45830 | M79: Passed | O79: 0.5 | P79: 1.0673
D80: Pause
D81: Release Call
A82: StormLine | B82: Employee makes a call | C82: - | D82: Place Call | F82: 45813 | G82: Passed | H82: 2180 | K82: https://confluence.nexteraenergy.com/x/S0buJQ | L82: 45830 | M82: Passed | N82: 1949 | O82: 2.86 | P82: 3.819 | Q82: https://confluence.nexteraenergy.com/x/S0buJQ
B83: IVR requests employee's input. Employee Presses 2 | C83: Press 2 | D83: Recognize ASM Message | I83: 1.7 | O83: 1.54 | P83: 2.1068
B84: Employee Presses 1 | C84: Press 1 | D84: Press 1
B85: System prompts | D85: Recognize Repeat of Dynamic Message | I85: 1.35 | O85: 1.28 | P85: 1.8613
B86: Customer hangs up | D86: Press 2
D87: Pause
D88: Release Call
A89: Wiredown | B89: Dial the FPL customer service number. Tester to call from a phone number which is not present in the FPL database and results in No ANI Match | C89: FPL customer service No | D89: Place Call | F89: 45813 | G89: Passed | H89: 4160 | K89: https://confluence.nexteraenergy.com/x/S0buJQ | L89: 45830 | M89: Passed | N89: 5419 | O89: 2.91 | P89: 16.4894 | Q89: https://confluence.nexteraenergy.com/x/S0buJQ
B90: Customer says down wire | C90: {Down wire} | D90: Recognize Greeting | I90: 1.18 | O90: 1.04 | P90: 1.3619
B91: System prompts | D91: Recognize Emergency Message | I91: 2.34 | O91: 2.65 | P91: 3.6096
B92: Customer waits as they are transfered to agent | C92: - | D92: Recognize Please Wait | I92: 0.6 | O92: 0.5 | P92: 1.0604
B93: System prompts | C93: - | D93: Recognize Menu | I93: 2.19 | O93: 0.35 | P93: 1.514
D94: Say
D95: Recognize Transfer to Agents | I95: 2.55 | O95: 1.65 | P95: 2.0225
D96: Release Call
A98: ANI Match Authentication with single address | B98: Dial the FPL customer service number. | C98: Gajendran Karthikeyan | D98: 45768 | E98: Not Run | I98: 45768 | J98: Not Run | N98: 45768 | O98: Not Run | S98: XDX-TC-18653
B99: System prompt Emergency situation message | D99: 45768 | E99: Not Run | I99: 45768 | J99: Not Run | N99: 45768 | O99: Not Run
B100: System prompt that account is located with phone | D100: 45768 | E100: Not Run | I100: 45768 | J100: Not Run | N100: 45768 | O100: Not Run
B101: Customer does not confirm service address | D101: 45768 | E101: Not Run | I101: 45768 | J101: Not Run | N101: 45768 | O101: Not Run
...

Sheet CS Field Service
U1: FPL NW Standard | Y1: Industry Standard
A2: Intergated Release | B2: Performance Testing Scenarios | C2: Functional Steps | D2: Performance Test Execution (Response Time Capturing page) | E2: Planned Execution Start Date | F2: Planned Execution End Date | G2: Rebased Execution Start Date | H2: Rebased Execution End Date | I2: Execution Status | J2: Performance Test Lead | K2: No.of requests | L2: Avg response time(s) | M2: 90%Line | N2: Rerun avg Response time for account 360 page with 2401 requestd | O2: Rerun 90%Line for account 360 page with 2401 requestd | P2: Planned Execution Start Date | Q2: Execution Status | R2: Avg response time(s ) | S2: 90%Line | T2: Comments/ | U2: FPL NW Application | V2: User/Data Load Volumetrics | W2: Average Response Time | X2: 90% Line | Y2: Average Response Time | Z2: 90% Line | AA2: Reasons for Deviations | AB2: How 90% Line is calculated for Current Performance Test | AC2: Performance test results csv files from Jmeter
A3: IR1 | B3: Appointment Booking( worktype as EESA) | C3: 1.Login to salesforce | E3: 45743 | F3: 45743 | G3: 45749 | H3: 45749 | I3: Passed | J3: Sravya Polavarapu | R3: Rerun avg Response time for account 360 page with 2401 requestd | S3: Rerun 90%Line for account 360 page with 2401 requestd | Y3: Average is useful, but is not as strict as 90% line. It allows for large deviations and diminishes their impact when averaged out with fast responses. Web focuses on 90% line since that metric will truly tell us how many transactions are past SLA. | Z3: 40% of users will leave a website if it takes more than 5 seconds to load. Aiming for a page load time under 5 seconds is crucial for a positive user experience and can even impact search engine rankings. | AB3: 90% Line automatically calculated in JMeter tool. | AC3: https://nee.sharepoint.com/teams/EXT_CIStoSAP/Shared%20Documents/Forms/AllItems.aspx?id=%2Fteams%2FEXT%5FCIStoSAP%2FShared%20Documents%2FOperational%20Readiness%20and%20Testing%2F00%2E%20Integrated%20Releases%2F01%2D%20Integrated%20Release%201%2E0%2F02%2E%20UAT%2F03%2E%20Performance%20Testing%2FUnified%20CRM%2D%20Performance%20Test%2FField%20Services&viewid=7c6b97d2%2De29a%2D4b27%2D98e7%2D3f5d5bd11dff&CT=1744734421771&OR=OWA%2DNT%2DMail&CID=fdad4da5%2D3ad1%2D9d3f%2Ddbc8%2Ddc1163ee8893&e=5%3A114072a8299643868b1c4fc0e1a4594b&sharingv2=true&fromShare=true&at=9&FolderCTID=0x012000D735ADCC1E28D24684C83D05ABBC84C7
C4: 2. Home page | E4: 45743 | F4: 45743 | G4: 45749 | H4: 45749 | I4: Passed | J4: Sunanda Poda
C5: 3. Search AccountNumber | D5: Search with account number page | E5: 45743 | F5: 45743 | G5: 45749 | H5: 45749 | I5: Passed | J5: Srividya Chamarthy | K5: 30 | L5: 0.249 | M5: 0.343
C6: 4. account Dashboard | D6: Loading account dashboard page | E6: 45743 | F6: 45743 | G6: 45749 | H6: 45749 | I6: Passed | K6: 30 | L6: 7.468 | M6: 7.616 | N6: 3.587 | O6: 3.841 | T6: SFAD-2104- Resolved
C7: 5. click on appointment | D7: Loading appointment page | E7: 45743 | F7: 45743 | G7: 45749 | H7: 45749 | I7: Passed | K7: 30 | L7: 2.139 | M7: 2.727 | R7: 3.587 | S7: 3.841
C8: 6. Click on worktype EESA_and_Next | D8: Worktype loading page | E8: 45743 | F8: 45743 | G8: 45749 | H8: 45749 | I8: Passed | K8: 30 | L8: 6.439 | M8: 9.683 | T8: SFFIELD-1756,SFFIELD-1797 to be closed and addressed in the story SFFIELD-1812
C9: 7. Click on time slot | D9: Appointment date and time slot page | E9: 45743 | F9: 45743 | G9: 45749 | H9: 45749 | I9: Passed | K9: 30 | L9: 2.604 | M9: 2.563
C10: 8. click on submit | D10: submitting appointment | E10: 45743 | F10: 45743 | G10: 45749 | H10: 45749 | I10: Passed | K10: 30 | L10: 7.431 | M10: 12.707 | T10: SFFIELD-1756,SFFIELD-1797 to be closed and addressed in the story SFFIELD-1812
A11: IR1 | B11: Appointment Booking( worktype as SURV) | C11: 1.Login to salesforce | E11: 45743 | F11: 45743 | G11: 45749 | H11: 45749 | I11: Passed
C12: 2. Home page | E12: 45743 | F12: 45743 | G12: 45749 | H12: 45749 | I12: Passed
C13: 3. Search AccountNumber | D13: Search with account number page | E13: 45743 | F13: 45743 | G13: 45749 | H13: 45749 | I13: Passed | K13: 30 | L13: 0.226 | M13: 0.277
C14: 4. account Dashboard | D14: Loading account dashboard page | E14: 45743 | F14: 45743 | G14: 45749 | H14: 45749 | I14: Passed | K14: 30 | L14: 8.001 | M14: 7.46 | N14: 3.587 | O14: 3.841 | T14: SFAD-2104- resolved
C15: 5. click on appointment | D15: Loading appintment page | E15: 45743 | F15: 45743 | G15: 45749 | H15: 45749 | I15: Passed | K15: 30 | L15: 2.074 | M15: 2.378 | R15: 3.587 | S15: 3.841
C16: 6. Click on worktype SURV | D16: Worktype_click_next | E16: 45743 | F16: 45743 | G16: 45749 | H16: 45749 | I16: Passed | K16: 30 | L16: 7.561 | M16: 11.679 | T16: SFFIELD-1756,SFFIELD-1797 to be closed and addressed in the story SFFIELD-1812
C17: 7. Click on time slot | D17: Appointment date and time slot page | E17: 45743 | F17: 45743 | G17: 45749 | H17: 45749 | I17: Passed | K17: 30 | L17: 2.596 | M17: 2.922
C18: 8. click on submit | D18: submitting appointment | E18: 45743 | F18: 45743 | G18: 45749 | H18: 45749 | I18: Passed | K18: 30 | L18: 8.236 | M18: 11.108 | T18: SFFIELD-1756,SFFIELD-1797 to be closed and addressed in the story SFFIELD-1812
A19: IR1 | B19: Appointment Booking( worktype as BEE) | C19: 1.Login to salesforce | E19: 45743 | F19: 45743 | G19: 45749 | H19: 45749 | I19: Passed
C20: 2. Home page | E20: 45743 | F20: 45743 | G20: 45749 | H20: 45749 | I20: Passed
C21: 3. Search AccountNumber | D21: Search with account number page | E21: 45743 | F21: 45743 | G21: 45749 | H21: 45749 | I21: Passed | K21: 30 | L21: 0.229 | M21: 0.3
C22: 4. account Dashboard | D22: Loading account dashboard page | E22: 45743 | F22: 45743 | G22: 45749 | H22: 45749 | I22: Passed | K22: 30 | L22: 7.61 | M22: 8.756 | N22: 3.587 | O22: 3.841 | T22: SFAD-2104- resolved
C23: 5. click on appointment | D23: Loading appointment page | E23: 45743 | F23: 45743 | G23: 45749 | H23: 45749 | I23: Passed | K23: 30 | L23: 2.156 | M23: 2.734 | R23: 3.587 | S23: 3.841
C24: 6. Click on worktype business energy evaluation | D24: loading worktype | E24: 45743 | F24: 45743 | G24: 45749 | H24: 45749 | I24: Passed | K24: 30 | L24: 7.105 | M24: 9.868 | T24: SFFIELD-1756,SFFIELD-1797 to be closed and addressed in the story SFFIELD-1812
C25: 7. Click on time slot | D25: Appointment date and time slot page | E25: 45743 | F25: 45743 | G25: 45749 | H25: 45749 | I25: Passed | K25: 30 | L25: 2.532 | M25: 3.044
C26: 8. click on submit | D26: submitting appointment | E26: 45743 | F26: 45743 | G26: 45749 | H26: 45749 | I26: Passed | K26: 30 | L26: 6.988 | M26: 8.371 | T26: SFFIELD-1756,SFFIELD-1797 to be closed and addressed in the story SFFIELD-1812
A27: IR1 | B27: API | C27: Energy Analyzer | E27: 45743 | F27: 45743 | G27: 45753 | H27: 45753 | I27: Passed | K27: 2000 | L27: 0.789 | M27: 1.301
A28: IR1 | B28: API | C28: Get Alerts | E28: 45743 | F28: 45743 | G28: 45753 | H28: 45753 | I28: Passed | K28: 2000 | L28: 0.563 | M28: 0.959
A30: IR2.0 | B30: Appointment Creation(Meter Maintainence} | C30: 1. Login to Salesforce | E30: 45984 | I30: Passed | K30: 30 | L30: 0.414 | M30: 0.45 | P30: 46009 | Q30: Passed | R30: 0.564 | S30: 0.765
C31: 2. Home Page | E31: 45984 | I31: Passed | K31: 30 | L31: 1.361 | M31: 0.524 | P31: 46009 | Q31: Passed | R31: 0.495 | S31: 0.655
C32: 3. Search Account Number | E32: 45984 | I32: Passed | K32: 30 | L32: 0.405 | M32: 0.439 | P32: 46009 | Q32: Passed | R32: 0.491 | S32: 0.599
C33: 4. Account Dashboard | E33: 45984 | I33: Failed | K33: 30 | L33: 6.069 | M33: 7.602 | P33: 46009 | Q33: Failed | R33: 6.864 | S33: 7.997 | T33: https://jira.nexteraenergy.com/browse/SFAD-9356/ converted to CS field issue: https://jira.nexteraenergy.com/browse/SFFIELD-3815
C34: 5.Click on Book Appointment | E34: 45984 | I34: Passed | K34: 30 | L34: 1.514 | M34: 1.667 | P34: 46009 | Q34: Passed | R34: 1.806 | S34: 1.948
C35: 6. Select Order Type and FMO Classification | E35: 45984 | I35: Passed | K35: 30 | L35: 0.434 | M35: 0.482 | P35: 46009 | Q35: Passed | R35: 0.604 | S35: 0.726
C36: 7. Click on NExt | E36: 45984 | I36: Passed | K36: 30 | L36: 2.063 | M36: 2.225 | P36: 46009 | Q36: Passed | R36: 2.495 | S36: 2.746
C37: 8. Select work type and click on Next | E37: 45984 | I37: Failed | K37: 30 | L37: 7.188 | M37: 8.28 | P37: 46009 | Q37: Failed | R37: 10.237 | S37: 10.128 | T37: https://jira.nexteraenergy.com/browse/SFFIELD-3709
C38: 9. Select 2 hrs slot | E38: 45984 | I38: Passed | K38: 30 | L38: 0.54 | M38: 2.183 | P38: 46009 | Q38: Passed | R38: 0.413 | S38: 0.291
C39: 10 . Submit appointment | E39: 45984 | I39: Failed | K39: 30 | L39: 8.774 | M39: 11.143 | P39: 46009 | Q39: Failed | R39: 14.377 | S39: 19.393 | T39: https://jira.nexteraenergy.com/browse/SFFIELD-3709
A41: IR2.0 | B41: Helper Ticket Creation | C41: 1. Login to salesforce | E41: 45984 | I41: Passed | K41: 100 | L41: 0.691 | M41: 0.52 | P41: 46009 | Q41: Passed | R41: 0.574 | S41: 0.644
C42: 2. Home Page | E42: 45984 | I42: Passed | K42: 100 | L42: 0.493 | M42: 0.461 | P42: 46009 | Q42: Passed | R42: 0.766 | S42: 0.643
C43: 3. Navigate to Field Force | E43: 45984 | I43: Passed | K43: 100 | L43: 1.123 | M43: 1.255 | P43: 46009 | Q43: Passed | R43: 1.412 | S43: 1.616
C44: 4. Navigate to service appointments | E44: 45984 | I44: Passed | K44: 100 | L44: 0.88 | M44: 1.082 | P44: 46009 | Q44: Passed | R44: 1.188 | S44: 1.325
C45: 5. Search for service appointment | E45: 45984 | I45: Passed | K45: 100 | L45: 0.649 | M45: 0.983 | P45: 46009 | Q45: Passed | R45: 1.09 | S45: 1.287
C46: 6. Open service appointment | E46: 45984 | I46: Passed | K46: 100 | L46: 1.467 | M46: 1.618 | P46: 46009 | Q46: Passed | R46: 2.02 | S46: 2.159
C47: 7. click on helper ticket create | E47: 45984 | I47: Passed | K47: 100 | L47: 0.12 | M47: 0.107 | P47: 46009 | Q47: Passed | R47: 0.15 | S47: 0.187
C48: 8. Click on proceed button | E48: 45984 | I48: Passed | K48: 100 | L48: 1.035 | M48: 1.195 | P48: 46009 | Q48: Passed | R48: 1.667 | S48: 1.5
A50: IR2.0 | B50: TimeSheets | C50: 1. Login to salesforce | E50: 45984 | I50: Passed | K50: 300 | L50: 0.613 | M50: 0.525 | P50: 46009 | Q50: Passed | R50: 0.549 | S50: 0.691
C51: 2. Home Page | E51: 45984 | I51: Passed | K51: 300 | L51: 0.523 | M51: 0.511 | P51: 46009 | Q51: Passed | R51: 0.591 | S51: 0.684
C52: 3. navigate to Timesheets | E52: 45984 | I52: Passed | K52: 300 | L52: 1.184 | M52: 1.369 | P52: 46009 | Q52: Passed | R52: 1.541 | S52: 1.703
C53: 4. Click on New Timesheets | E53: 45984 | I53: Passed | K53: 300 | L53: 0.823 | M53: 0.962 | P53: 46009 | Q53: Passed | R53: 0.988 | S53: 1.157
C54: 5. Enter Timesheet details and save | E54: 45984 | I54: Passed | K54: 300 | L54: 0.349 | M54: 0.405 | P54: 46009 | Q54: Passed | R54: 0.492 | S54: 0.538
C55: 6. Submit Timesheet | E55: 45984 | I55: Passed | K55: 300 | L55: 0.453 | M55: 0.548 | P55: 46009 | Q55: Passed | R55: 0.582 | S55: 0.7
C56: 7. Submit 5 Timesheet entries | E56: 45984 | I56: Passed | K56: 300 | L56: 0.485 | M56: 0.596 | P56: 46009 | Q56: Passed | R56: 0.586 | S56: 0.722
C57: 8. Submit 20 Timesheet entries | E57: 45984 | I57: Passed | K57: 300 | L57: 0.502 | M57: 0.634 | P57: 46009 | Q57: Passed | R57: 0.551 | S57: 0.678
A59: IR2.0 | B59: API | C59: Meter Reading Range | E59: 45989 | I59: Passed | K59: 5000 | L59: 1.296 | M59: 1.507 | P59: 46009 | Q59: Passed | R59: 1.342 | S59: 1.582
B60: API | C60: Send Letter | E60: 45989 | I60: Passed | K60: 5000 | L60: 0.648 | M60: 0.992 | P60: 46009 | Q60: Passed | R60: 1.056 | S60: 0.919
B61: API | C61: TimeSheets | E61: 45989 | I61: Passed | K61: 5000 | L61: 0.511 | M61: 0.701 | P61: 46009 | Q61: Passed | R61: 0.51 | S61: 0.696
B62: API | C62: Customer Interactions | E62: 45989 | I62: Passed | K62: 30000 | L62: 0.372 | M62: 0.726 | P62: 46009 | Q62: Passed | R62: 0.689 | S62: 1.016
B63: API | C63: Field Note | E63: 45989 | I63: Passed | K63: 5000 | L63: 1.498 | M63: 1.135 | P63: 46009 | Q63: Passed | R63: 3.068 | S63: 1.853
B64: API | C64: Meter Ping | E64: 45989 | I64: Passed | K64: 5000 | L64: 12.163 | M64: 13.009 | P64: 46009 | Q64: Passed | R64: 46.773 | S64: 52.179 | T64: https://jira.nexteraenergy.com/browse/SFFIELD-3797 (CLOSED)
B66: Platform events | C66: 1. work order creation(RMM) | E66: 45981 | I66: Passed | K66: 6000
C67: 2. Work order Update as scheduled | E67: 45989 | I67: Passed | K67: 6000
C68: 3. Work Order Update as Dispatched | E68: 46363 | I68: Passed | K68: 6000 | T68: https://jira.nexteraenergy.com/browse/SFFIELD-3795
C69: 4. Work order update as Enroute | E69: 46363 | I69: Passed | K69: 6000
C70: 5. Work Order update as InProgress | E70: 46363 | I70: Passed | K70: 6000
C71: 6. Work Order update as Cannot Complete | E71: 46364 | I71: Passed | K71: 6000
B73: API | C73: MeterPing | E73: 46014 | I73: Passed | K73: 5000 | L73: 27.626 | M73: 51.512 | T73: https://confluence.nexteraenergy.com/spaces/MULESFTINT/pages/610788133/IR2.0+Field+Service+-+Meter+Ping+-+CRM+Field

Sheet DCP- Customer Communications  
A1: Performance Testing Scenarios | B1: Functional Steps | C1: Planned Execution Date | D1: Execution Status | E1: Performance Test Lead

Sheet Integrations Mulesfot
A1: Performance Testing Scenarios | B1: Functional Steps | C1: No.of requests | D1: Avg response time(ms) | E1: 90%Line (ms) | F1: Legacy Standard | J1: FPL NW Standard | N1: Industry Standard | R1: Planned Execution Date | S1: Execution Status | T1: Performance Test Lead | U1: Results
F2: Legacy Application | G2: User/Data Load Volumetrics | H2: Average Response Time | I2: 90% Line | J2: FPL NW Application | K2: User/Data Load Volumetrics | L2: Average Response Time | M2: 90% Line | N2: Average Response Time | O2: 90% Line | P2: Reasons for Deviations | Q2: How 90% Line is calculated for Current Performance Test
A3: Moveout | B3: Moveout Submission | C3: 2400 | D3: 3318 | E3: 3479 | F3: No Legacy Standard as API's developed as brand new API's | Q3: We Performed Performance testing in J-meter and these 90% Line Results captured from tool. | R3: 45736 | S3: Passed | T3: Kuna, Sudhir kumar
B4: Validate End Date | C4: 2400 | D4: 666 | E4: 741 | Q4: We Performed Performance testing in J-meter and these 90% Line Results captured from tool. | R4: 45735 | S4: Passed
A5: Manage Programs | B5: Manage Programs enrollment | C5: 2400 | D5: 440 | E5: 566 | Q5: We Performed Performance testing in J-meter and these 90% Line Results captured from tool. | R5: 45736 | S5: Passed | T5: Koka, Srinivasu Kuna Sudhir kumar
B6: getDetails | C6: 2400 | D6: 1010 | E6: 1533 | Q6: We Performed Performance testing in J-meter and these 90% Line Results captured from tool. | R6: 45734 | S6: Passed
B7: getEligiblility | C7: 2400 | D7: 1172 | E7: 1760 | Q7: We Performed Performance testing in J-meter and these 90% Line Results captured from tool. | R7: 45734 | S7: Passed
B8: postCorrespondence | C8: 2400 | D8: 393 | E8: 425 | Q8: We Performed Performance testing in J-meter and these 90% Line Results captured from tool. | R8: 45735 | S8: Passed | U8: https://confluence.nexteraenergy.com/pages/viewpage.action?pageId=610763872&preview=/610763872/610763899/postCorresspondance-utility-papi-2400-user.pdf
A9: Account 360 | B9: Account 360 | C9: 2400 | D9: 948 | E9: 1205 | Q9: We Performed Performance testing in J-meter and these 90% Line Results captured from tool. | R9: 45735 | S9: Passed | T9: Koka, Srinivasu Kuna Sudhir kumar | U9: https://confluence.nexteraenergy.com/display/MULESFTINT/Performance+Test+Results%3A+account360+and+getAlerts?preview=/604966771/604972120/account360.pdf
B10: getAlerts | C10: 2400 | D10: 544 | E10: 650 | Q10: We Performed Performance testing in J-meter and these 90% Line Results captured from tool. | R10: 45735 | S10: Passed | U10: https://confluence.nexteraenergy.com/display/MULESFTINT/Performance+Test+Results%3A+account360+and+getAlerts?preview=/604966771/604972134/getAlerts.pdf
A11: Account maintenance | B11: Validate Email | C11: 4800 | D11: 981 | E11: 1062 | Q11: We Performed Performance testing in J-meter and these 90% Line Results captured from tool. | R11: 45734 | S11: Passed | T11: Venkatesh | U11: https://confluence.nexteraenergy.com/display/MULESFTINT/Performance+Test+Results+%3A+AccountMaintenance-papi?preview=/610765166/610768760/validate-email.pdf
B12: Validate Phone | C12: 4800 | D12: 332 | E12: 445 | Q12: We Performed Performance testing in J-meter and these 90% Line Results captured from tool. | R12: 45734 | S12: Passed | U12: https://confluence.nexteraenergy.com/display/MULESFTINT/Performance+Test+Results+%3A+AccountMaintenance-papi?preview=/610765166/610765213/validate-Phone.pdf
B13: Validate address | C13: 4800 | D13: 919 | E13: 2503 | Q13: We Performed Performance testing in J-meter and these 90% Line Results captured from tool. | R13: 45734 | S13: Passed | U13: https://confluence.nexteraenergy.com/display/MULESFTINT/Performance+Test+Results+%3A+AccountMaintenance-papi?preview=/610765166/610765184/validateAddress-papi.pdf
B14: Update Phone | C14: 2400 | D14: 1905 | E14: 2024 | Q14: We Performed Performance testing in J-meter and these 90% Line Results captured from tool. | R14: 45736 | S14: Passed
B15: Update Email | C15: 2400 | D15: 998 | E15: 1131 | Q15: We Performed Performance testing in J-meter and these 90% Line Results captured from tool. | R15: 45736 | S15: Passed
B16: Update mailining address | C16: 2400 | D16: 514 | E16: 674 | Q16: We Performed Performance testing in J-meter and these 90% Line Results captured from tool. | R16: 45736 | S16: Passed
B17: Update Customer ID | C17: 2400 | D17: 2829 | E17: 3100 | Q17: We Performed Performance testing in J-meter and these 90% Line Results captured from tool. | R17: 45735 | S17: Passed
A18: Utility | B18: postCorrespondence | C18: 4800 | D18: 402 | E18: 519 | Q18: We Performed Performance testing in J-meter and these 90% Line Results captured from tool. | R18: 45736 | S18: Passed

Sheet Case Management
N1: Legacy Standard | R1: FPL NW Standard | V1: Industry Standard
A2: Integrated Release | B2: Performance Testing Scenarios | C2: Functional Steps | D2: Performance Test Execution (Response Time Capturing page) | E2: Planned Execution Start Date | F2: Planned Execution End Date | G2: Rebased Execution Start Date | H2: Rebased Execution End Date | I2: Execution Status | J2: Performance Test Lead | K2: No.of requests | L2: Avg response time(s) | M2: 90%Line | N2: Legacy Application | O2: User/Data Load Volumetrics | P2: Average Response Time | Q2: 90% Line | R2: Legacy Application | S2: User/Data Load Volumetrics | T2: Average Response Time | U2: 90% Line | V2: Average Response Time | W2: 90% Line | X2: Reasons for Deviations | Y2: How 90% Line is calculated for Current Performance Test
B3: Case Creation closure (Update personal Information) | C3: 1. Login to salesforce | D3: No | E3: 45743 | F3: 45743 | G3: 45737 | H3: 45737 | I3: Passed | J3: Sravya Polavarapu | N3: No benchmark data currently available for Case Management since the unified CRM system newly developed | R3: No benchmark data currently available for Case Management since the unified CRM system newly developed | V3: Average is useful, but is not as strict as 90% line. It allows for large deviations and diminishes their impact when averaged out with fast responses. Web focuses on 90% line since that metric will truly tell us how many transactions are past SLA. | W3: 40% of users will leave a website if it takes more than 5 seconds to load. Aiming for a page load time under 5 seconds is crucial for a positive user experience and can even impact search engine rankings. | Y3: 90% Line automatically calculated in JMeter tool.
C4: 2. Homepage | D4: No | E4: 45743 | F4: 45743 | G4: 45737 | H4: 45737 | I4: Passed | J4: Sunanda Poda
C5: 3. click on create case | D5: Yes, Create Case page loading time Verify Page Load time for Create Case functionaility, how the page behaves under different user load scenarios, Time for all page requests to receive their response from server. | E5: 45743 | F5: 45743 | G5: 45737 | H5: 45737 | I5: Passed | J5: Srividya Chamarthy | K5: 494 | L5: 0.124 | M5: 0.142
C6: 4. select sub category as update personal information | D6: yes | E6: 45743 | F6: 45743 | G6: 45737 | H6: 45737 | I6: Passed | K6: 494 | L6: 0.198 | M6: 0.238
C7: 5. enter sub category details | D7: yes | E7: 45743 | F7: 45743 | G7: 45737 | H7: 45737 | I7: Passed | K7: 494 | L7: 0.237 | M7: 0.277
C8: 6. click on submit | D8: Yes, Case Creation page loading time | E8: 45743 | F8: 45743 | G8: 45737 | H8: 45737 | I8: Passed | K8: 494 | L8: 0.96 | M8: 1.117
C9: 7. Task creation | D9: yes | E9: 45743 | F9: 45743 | G9: 45743 | H9: 45743 | I9: Passed | K9: 494 | L9: 0.603 | M9: 0.933
C10: 8. task close | D10: Yes, | E10: 45743 | F10: 45743 | G10: 45743 | H10: 45743 | I10: Passed | K10: 494 | L10: 0.762 | M10: 0.889
C11: 9. case close | D11: Yes, Case Creation page loading time | E11: 45743 | F11: 45743 | G11: 45743 | H11: 45743 | I11: Passed | K11: 494 | L11: 1.197 | M11: 1.343
B12: Case Creation and close (fpl.com/mobileapp) | C12: 1. Login to salesforce | E12: 45743 | F12: 45743 | G12: 45737 | H12: 45737 | I12: Passed
C13: 2. Homepage | E13: 45743 | F13: 45743 | G13: 45737 | H13: 45737 | I13: Passed
C14: 3. click on create case | D14: yes | E14: 45743 | F14: 45743 | G14: 45737 | H14: 45737 | I14: Passed | K14: 285 | L14: 0.13 | M14: 0.151
C15: 4. select fpl.com/mobileapp | D15: yes | E15: 45743 | F15: 45743 | G15: 45737 | H15: 45737 | I15: Passed | K15: 285 | L15: 0.201 | M15: 0.238
C16: 5. select subcategory as fpl.com/mobileapp | D16: yes | E16: 45743 | F16: 45743 | G16: 45737 | H16: 45737 | I16: Passed | K16: 285 | L16: 0.23 | M16: 0.271
C17: 6. click on submit | D17: yes | E17: 45743 | F17: 45743 | G17: 45737 | H17: 45737 | I17: Passed | K17: 285 | L17: 0.955 | M17: 1.058
C18: 7. Task creation | D18: yes | E18: 45743 | F18: 45743 | G18: 45743 | H18: 45743 | I18: Passed | K18: 285 | L18: 0.584 | M18: 0.89
C19: 8. task close | D19: yes | E19: 45743 | F19: 45743 | G19: 45743 | H19: 45743 | I19: Passed | K19: 285 | L19: 0.775 | M19: 0.896
C20: 9.case close | D20: yes | E20: 45743 | F20: 45743 | G20: 45743 | H20: 45743 | I20: Passed | K20: 285 | L20: 1.166 | M20: 1.298
B21: Case Creation and close(Moveout date correction) | C21: 1. Login to salesforce | E21: 45743 | F21: 45743 | G21: 45737 | H21: 45737 | I21: Passed
C22: 2. Homepage | E22: 45743 | F22: 45743 | G22: 45737 | H22: 45737 | I22: Passed
C23: 3. click on create case | D23: "Yes, Create Case page loading time Verify Page Load time for Create Case functionaility, how the page behaves under different user load scenarios, Time for all page requests to receive their response from server. " | E23: 45743 | F23: 45743 | G23: 45737 | H23: 45737 | I23: Passed | K23: 399 | L23: 0.124 | M23: 0.148
C24: 4. select subcategory as moveout date correction | D24: Yes, | E24: 45743 | F24: 45743 | G24: 45737 | H24: 45737 | I24: Passed | K24: 399 | L24: 0.199 | M24: 0.249
C25: 5. enter sub category details | D25: Yes, | E25: 45743 | F25: 45743 | G25: 45737 | H25: 45737 | I25: Passed | K25: 399 | L25: 0.464 | M25: 0.536
C26: 6. click on submit | D26: Yes, Case Creation page loading time | E26: 45743 | F26: 45743 | G26: 45737 | H26: 45737 | I26: Passed | K26: 399 | L26: 1.381 | M26: 1.521
C27: 7. task creation | D27: Yes, | E27: 45743 | F27: 45743 | G27: 45743 | H27: 45743 | I27: Passed | K27: 399 | L27: 0.573 | M27: 0.896
C28: 8. task close | D28: Yes, | E28: 45743 | F28: 45743 | G28: 45743 | H28: 45743 | I28: Passed | K28: 399 | L28: 1.165 | M28: 1.385
C29: 9. case close | D29: Yes, | E29: 45743 | F29: 45743 | G29: 45743 | H29: 45743 | I29: Passed | K29: 399 | L29: 1.172 | M29: 1.287
B30: Case Creation and close (Moveout master account) | C30: 1. Login to salesforce | E30: 45743 | F30: 45743 | G30: 45737 | H30: 45737 | I30: Passed
C31: 2. Homepage | E31: 45743 | F31: 45743 | G31: 45737 | H31: 45737 | I31: Passed
C32: 3. click on create case | D32: yes | E32: 45743 | F32: 45743 | G32: 45737 | H32: 45737 | I32: Passed | K32: 494 | L32: 0.122 | M32: 0.152
C33: 4. select subactegory as moveout master account | D33: Yes, | E33: 45743 | F33: 45743 | G33: 45737 | H33: 45737 | I33: Passed | K33: 494 | L33: 0.199 | M33: 0.235
C34: 5. enter sub category details | D34: yes | E34: 45743 | F34: 45743 | G34: 45737 | H34: 45737 | I34: Passed | K34: 494 | L34: 0.556 | M34: 0.644
C35: 6. click on submit | D35: Yes, | E35: 45743 | F35: 45743 | G35: 45737 | H35: 45737 | I35: Passed | K35: 494 | L35: 1.335 | M35: 1.505
C36: 7. Task creation | D36: Yes, | E36: 45743 | F36: 45743 | G36: 45743 | H36: 45743 | I36: Passed | K36: 494 | L36: 0.577 | M36: 0.9
C37: 8. task close | D37: Yes, | E37: 45743 | F37: 45743 | G37: 45743 | H37: 45743 | I37: Passed | K37: 494 | L37: 0.77 | M37: 0.888
C38: 9. case close | D38: Yes, | E38: 45743 | F38: 45743 | G38: 45743 | H38: 45743 | I38: Passed | K38: 494 | L38: 1.19 | M38: 1.334
B39: Case Creation and close(Light Removal) | C39: 1. Login to salesforce | E39: 45743 | F39: 45743 | G39: 45737 | H39: 45737 | I39: Passed
C40: 2. Homepage | E40: 45743 | F40: 45743 | G40: 45737 | H40: 45737 | I40: Passed
C41: 3. click on create case | D41: Yes, | E41: 45743 | F41: 45743 | G41: 45737 | H41: 45737 | I41: Passed | K41: 190 | L41: 0.116 | M41: 0.136
C42: 4. select subcategory as light removal | D42: Yes, | E42: 45743 | F42: 45743 | G42: 45737 | H42: 45737 | I42: Passed | K42: 190 | L42: 0.197 | M42: 0.229
C43: 5. enter sub category details | D43: Yes, | E43: 45743 | F43: 45743 | G43: 45737 | H43: 45737 | I43: Passed | K43: 190 | L43: 0.472 | M43: 0.549
C44: 6. click on submit | D44: Yes, | E44: 45743 | F44: 45743 | G44: 45737 | H44: 45737 | I44: Passed | K44: 190 | L44: 1.347 | M44: 1.519
C45: 7. Task creation | D45: Yes, | E45: 45743 | F45: 45743 | G45: 45743 | H45: 45743 | I45: Passed | K45: 190 | L45: 0.554 | M45: 0.882
C46: 8. task close | D46: Yes, | E46: 45743 | F46: 45743 | G46: 45743 | H46: 45743 | I46: Passed | K46: 190 | L46: 1.201 | M46: 1.362
C47: 9. case close | D47: Yes, | E47: 45743 | F47: 45743 | G47: 45743 | H47: 45743 | I47: Passed | K47: 190 | L47: 1.144 | M47: 1.308
B48: Case Creation and close(billing programs fixed rate) | C48: 1. Login to salesforce | E48: 45743 | F48: 45743 | G48: 45737 | H48: 45737 | I48: Passed
C49: 2. Homepage | E49: 45743 | F49: 45743 | G49: 45737 | H49: 45737 | I49: Passed
C50: 3. click on create case | D50: Yes, | E50: 45743 | F50: 45743 | G50: 45737 | H50: 45737 | I50: Passed | K50: 1178 | L50: 0.124 | M50: 0.151
C51: 4. select subcategory as billing programs-fixed rate | D51: Yes, | E51: 45743 | F51: 45743 | G51: 45737 | H51: 45737 | I51: Passed | K51: 1178 | L51: 0.203 | M51: 0.241
C52: 5. enter sub category details | D52: Yes, | E52: 45743 | F52: 45743 | G52: 45737 | H52: 45737 | I52: Passed | K52: 1178 | L52: 0.235 | M52: 0.283
C53: 6. click on submit | D53: Yes, | E53: 45743 | F53: 45743 | G53: 45737 | H53: 45737 | I53: Passed | K53: 1178 | L53: 0.947 | M53: 1.076
C54: 7. Task creation | D54: Yes, | E54: 45743 | F54: 45743 | G54: 45743 | H54: 45743 | I54: Passed | K54: 1178 | L54: 0.568 | M54: 0.901
C55: 8. task close | D55: Yes, | E55: 45743 | F55: 45743 | G55: 45743 | H55: 45743 | I55: Passed | K55: 1178 | L55: 0.777 | M55: 0.902
C56: 9.case close | D56: Yes, | E56: 45743 | F56: 45743 | G56: 45743 | H56: 45743 | I56: Passed | K56: 1178 | L56: 1.195 | M56: 1.332
A58: IR2.0 | B58: Manual case Creation(Franchise fee enquiry As subcategory) | C58: 1. Login to salesforce | E58: 45983 | I58: Passed | K58: 5000 | L58: 0.432 | M58: 0.487
C59: 2. Home Page | E59: 45983 | I59: Passed | K59: 5000 | L59: 0.412 | M59: 0.468
C60: 3. Click on createcase | D60: Yes, | E60: 45983 | I60: Passed | K60: 5000 | L60: 1.138 | M60: 1.245
C61: 4.Select franchise fee enquiry | D61: Yes, | E61: 45983 | I61: Passed | K61: 5000 | L61: 1.217 | M61: 1.354
C62: 5. Submit Case | D62: Yes, | E62: 45983 | I62: Passed | K62: 5000 | L62: 2.346 | M62: 2.598
C63: 6. Click on created case | D63: Yes, | E63: 45983 | I63: Passed | K63: 5000 | L63: 0.43 | M63: 0.53
C64: 7. Click on New Task | D64: Yes, | E64: 45983 | I64: Passed | K64: 5000 | L64: 0.238 | M64: 0.22
C65: 8. Create Task | D65: Yes, | E65: 45983 | I65: Passed | K65: 5000 | L65: 0.713 | M65: 0.855
C66: 9. Close Task | D66: Yes, | E66: 45983 | I66: Passed | K66: 5000 | L66: 0.744 | M66: 0.88
C67: 10.Change owner | D67: Yes, | E67: 45983 | I67: Passed | K67: 5000 | L67: 1.819 | M67: 2.188
C68: 11. Click on Edit Case | D68: Yes, | E68: 45983 | I68: Passed | K68: 5000 | L68: 1.35 | M68: 1.317
C69: 12. Choose Subcategory Details page | D69: Yes, | E69: 45983 | I69: Passed | K69: 5000 | L69: 1.141 | M69: 1.11
C70: 13. Close Case | D70: Yes, | E70: 45983 | I70: Passed | K70: 5000 | L70: 1.268 | M70: 1.638
A72: IR2.0 | B72: Bulk Updates(Manual Cases) | C72: 1. Login to Salesforce | E72: 45983 | I72: Passed | K72: 5000 | L72: 0.424 | M72: 0.405
C73: 2. Home Page | E73: 45983 | I73: Passed | K73: 5000 | L73: 0.403 | M73: 0.478
C74: 3. Navigate to case List View | E74: 45983 | I74: Passed | K74: 5000 | L74: 0.524 | M74: 0.616
C75: 4. Select Caes from the list | E75: 45983 | I75: Passed | K75: 5000 | L75: 0.966 | M75: 1.198
C76: 5. Change owner | E76: 45983 | I76: Passed | K76: 5000 | L76: 1.588 | M76: 1.784
C77: 6. Click on Update | E77: 45983 | I77: Passed | K77: 5000 | L77: 0.182 | M77: 0.225
C78: 7. Submit Update | E78: 45983 | I78: Passed | K78: 5000 | L78: 1.376 | M78: 1.454
A80: IR2.0 | B80: Bulk Updates(BPEM Cases- C200), Taylor Trang - recommended mix of SAP BPEMS - Meter to Cash BPEM - (IN, MR, BL): EQ2 have enough customer to test not in EQ1 mix of all BPEMs(IN,MR, BL)- 5000 SAP automation team - Megan's - Raja | C80: 1. Login to Salesforce | E80: 45988 | I80: Passed | K80: 5000 | L80: 0.43 | M80: 0.411
C81: 2. Home Page | E81: 45988 | I81: Passed | K81: 5000 | L81: 0.413 | M81: 0.493
C82: 3. Navigate to case List View | E82: 45988 | I82: Passed | K82: 5000 | L82: 0.573 | M82: 0.679
C83: 4. Select Caes from the list | E83: 45988 | I83: Passed | K83: 5000 | L83: 1.296 | M83: 1.595
C84: 5. Change owner | E84: 45988 | I84: Passed | K84: 5000 | L84: 1.577 | M84: 1.994
C85: 6. Click on Update | E85: 45988 | I85: Passed | K85: 5000 | L85: 0.19 | M85: 0.236
C86: 7. Submit Update | E86: 45988 | I86: Passed | K86: 5000 | L86: 1.476 | M86: 2.071
A89: IR2.0 | B89: BPEM Cases(Task Creation,Closure, Close Case) | C89: 1. Login to Salesforce | E89: 45988 | I89: Passed | K89: 5000 | L89: 0.473 | M89: 0.542
C90: 2. Home Pgae | E90: 45988 | I90: Passed | K90: 5000 | L90: 0.427 | M90: 0.394
C91: 3. Global search for Case Number | E91: 45988 | I91: Passed | K91: 5000 | L91: 0.42 | M91: 0.541
C92: 4. Click on Open case | E92: 45988 | I92: Passed | K92: 5000 | L92: 2.683 | M92: 3.013
C93: 5. Click On New Task | E93: 45988 | I93: Passed | K93: 5000 | L93: 0.231 | M93: 0.294
C94: 6. Create Task | E94: 45988 | I94: Passed | K94: 5000 | L94: 0.693 | M94: 0.82
C95: 7. Close Task | E95: 45988 | I95: Passed | K95: 5000 | L95: 0.729 | M95: 0.874
C96: 8.Change Owner | E96: 45988 | I96: Passed | K96: 5000 | L96: 1.854 | M96: 2.389
C97: 9. Click on Edit case | E97: 45988 | I97: Passed | K97: 5000 | L97: 1.274 | M97: 1.596
C98: 10. Choose SubCategory details Page | E98: 45988 | I98: Passed | K98: 5000 | L98: 1.141 | M98: 1.317
C99: 11. Close Case | E99: 45988 | I99: Passed | K99: 5000 | L99: 1.794 | M99: 2.235

Sheet IR2 Performance Testing Status
A1: IR2 Performance Testing Results
A2: Workstreams Involved | B2: Total Test Scenarios | C2: Scenarios Executed | D2: Scenarios Passed | E2: Scenarios Failed | F2: Pass % | G2: Status (Pass/Fail) | H2: Comments
A3: Case Management | B3: 4 | C3: 4 | D3: 4 | E3: 0 | F3: 1 | G3: 4 scenarios Passed | H3: Signed off
A4: CS Field Services | B4: 10 | C4: 10 | D4: 7 | E4: 3 | F4: 0.7 | G4: 12/22:Out of 10 planned scenarios, 10 scenarios executed (8 passed, 2 failed) | H4: https://jira.nexteraenergy.com/browse/SFFIELD-3795
H5: https://jira.nexteraenergy.com/browse/SFFIELD-3797
H6: https://jira.nexteraenergy.com/browse/SFFIELD-3709

Sheet Employee Desktop
S1: Legacy Standard | W1: FPL NW Standard | AA1: Industry Standard
A2: Integrated Release | B2: Performance Testing Scenarios | C2: Functional Steps | D2: Performance Test Execution (Response Time Capturing page) | E2: Planned Execution Start Date | F2: Planned Execution End Date | G2: Rebased Execution Start Date | H2: Rebased Execution End Date | I2: Execution Status | J2: Defect | K2: Performance Test Lead | L2: No.of requests | M2: Average response time(s) | N2: 90%Line | O2: Rerun avg Response time for account 360 page | P2: Rerun 90%Line for account 360 page | Q2: Comments | R2: Performance test results csv files from jmeter | S2: Legacy Application | T2: User/Data Load Volumetrics | U2: Average Response Time | V2: 90% Line | W2: FPL NW Application | X2: User/Data Load Volumetrics | Y2: Average Response Time | Z2: 90% Line | AA2: Average Response Time | AB2: 90% Line | AC2: Reasons for Deviations | AD2: How 90% Line is calculated for Current Performance Test
B3: Search | C3: 1.Login to Salesforce | E3: 45743 | F3: 45743 | G3: 45743 | H3: 45743 | I3: Passed | K3: Sravya Polavarapu | AA3: Average is useful, but is not as strict as 90% line. It allows for large deviations and diminishes their impact when averaged out with fast responses. Web focuses on 90% line since that metric will truly tell us how many transactions are past SLA. | AB3: 40% of users will leave a website if it takes more than 5 seconds to load. Aiming for a page load time under 5 seconds is crucial for a positive user experience and can even impact search engine rankings. | AD3: 90% Line automatically calculated in JMeter tool.
C4: 2. HomePage | E4: 45743 | F4: 45743 | G4: 45743 | H4: 45743 | I4: Passed | K4: Sunanda Poda
C5: 3.Search AccountNumber | D5: yes, search with accountnumber | E5: 45743 | F5: 45743 | G5: 45743 | H5: 45743 | I5: Passed | K5: Srividya Chamarthy | L5: 2219 | M5: 0.297 | N5: 0.248
C6: 4.Search AccountName | D6: search with account name | E6: 45743 | F6: 45743 | G6: 45743 | H6: 45743 | I6: Passed | L6: 2210 | M6: 0.385 | N6: 0.476
C7: 5. Search BusinessPartnerId | D7: search with business partner id | E7: 45743 | F7: 45743 | G7: 45743 | H7: 45743 | I7: Passed | L7: 2202 | M7: 0.18 | N7: 0.213
C8: 6. Contract Number | D8: search with contract number | E8: 45743 | F8: 45743 | G8: 45743 | H8: 45743 | I8: Passed | L8: 2205 | M8: 0.204 | N8: 0.223
C9: 7. Search Email address | D9: search with email address | E9: 45743 | F9: 45743 | G9: 45743 | H9: 45743 | I9: Passed | L9: 2200 | M9: 2.708 | N9: 3.032
C10: 8. Search PhoneNUmber | D10: search with phone number | E10: 45743 | F10: 45743 | G10: 45743 | H10: 45743 | I10: Passed | L10: 2200 | M10: 4.67 | N10: 4.965
C11: 9. Search SSN/SIN | D11: searchwith SSN/SIN | E11: 45743 | F11: 45743 | G11: 45743 | H11: 45743 | I11: Passed | L11: 2200 | M11: 0.201 | N11: 0.244
C12: 10. Search TaxId | D12: Search with taxid | E12: 45743 | F12: 45743 | G12: 45743 | H12: 45743 | I12: Passed | L12: 2200 | M12: 0.159 | N12: 0.176
C13: 11. Search InstallationNUmber | D13: Search with Installation NUmber | E13: 45743 | F13: 45743 | G13: 45743 | H13: 45743 | I13: Passed | L13: 2207 | M13: 0.18 | N13: 0.213
C14: 12. Search MeterNUmber | D14: Search with meter number | E14: 45743 | F14: 45743 | G14: 45743 | H14: 45743 | I14: Passed | L14: 2201 | M14: 1.556 | N14: 1.677
C15: 13. Search Premise Number | D15: Search with premise number | E15: 45743 | F15: 45743 | G15: 45743 | H15: 45743 | I15: Passed | L15: 2200 | M15: 0.191 | N15: 0.215
B16: Account Maintainence (phone and email) | C16: 1. Login to salesforce | E16: 45744 | F16: 45744 | G16: 45748 | H16: 45748 | I16: Passed | Q16: Open Known Risk: https://jira.nexteraenergy.com/browse/SFAD-1363 Defect: https://jira.nexteraenergy.com/browse/SFAD-2104 we will retest this issue along with Field Testing, hence passing this test case conditionally, Results confluence Page: https://confluence.nexteraenergy.com/display/FPLS/Performance+Testing+Results+for+Unified+CRM+Project | R16: acc_main_phone_email
C17: 2.homepage | E17: 45744 | F17: 45744 | G17: 45748 | H17: 45748 | I17: Passed
C18: 3.Search AccountNumber | D18: Search with account number | E18: 45744 | F18: 45744 | G18: 45748 | H18: 45748 | I18: Passed | L18: 2401 | M18: 0.267 | N18: 0.309 | O18: 0.267 | P18: 0.309
C19: 4.account dashboard | D19: Laoding account dashboard page | E19: 45744 | F19: 45744 | G19: 45748 | H19: 45748 | I19: Passed | L19: 2401 | M19: 6.827 | N19: 7.495 | O19: 3.587 | P19: 3.841
C20: 5. click on account maintainence | D20: account maintaience page loading time | E20: 45744 | F20: 45744 | G20: 45748 | H20: 45748 | I20: Passed | L20: 2401 | M20: 3.942 | N20: 4.278 | O20: 3.942 | P20: 4.278
C21: 6. select phone and email | D21: Loading phone and email page | E21: 45744 | F21: 45744 | G21: 45748 | H21: 45748 | I21: Passed | L21: 2400 | M21: 0.144 | N21: 0.101 | O21: 0.144 | P21: 0.101
C22: 7. verify email | D22: verify email | E22: 45744 | F22: 45744 | G22: 45748 | H22: 45748 | I22: Passed | L22: 2399 | M22: 2.069 | N22: 2.215 | O22: 2.069 | P22: 2.215
C23: 8. verify phone | D23: verify phone | E23: 45744 | F23: 45744 | G23: 45748 | H23: 45748 | I23: Passed | L23: 2399 | M23: 1.553 | N23: 1.663 | O23: 1.553 | P23: 1.663
C24: 9. click on next (updated email and phone) | D24: updating phone and email page | E24: 45744 | F24: 45744 | G24: 45748 | H24: 45748 | I24: Passed | L24: 2398 | M24: 5.011 | N24: 5.48 | O24: 5.011 | P24: 5.48
B25: Account Maintainence(Res acc-customerid | C25: 1. Login to salesforce | E25: 45744 | F25: 45744 | G25: 45748 | H25: 45748 | I25: Passed | Q25: Open Known Risk: https://jira.nexteraenergy.com/browse/SFAD-1363 Defect: https://jira.nexteraenergy.com/browse/SFAD-2104 we will retest this issue along with Field Testing, hence passing this test case conditionally, Results confluence Page: https://confluence.nexteraenergy.com/display/FPLS/Performance+Testing+Results+for+Unified+CRM+Project | R25: Acc_main_res_customerid
C26: 2.homepage | E26: 45744 | F26: 45744 | G26: 45748 | H26: 45748 | I26: Passed
C27: 3.Search AccountNumber | D27: Search with account number | E27: 45744 | F27: 45744 | G27: 45748 | H27: 45748 | I27: Passed | L27: 2402 | M27: 0.277 | N27: 0.255 | O27: 0.277 | P27: 0.255
C28: 4.account dashboard | D28: Laoding account dashboard page | E28: 45744 | F28: 45744 | G28: 45748 | H28: 45748 | I28: Passed | L28: 2402 | M28: 7.229 | N28: 8.253 | O28: 3.587 | P28: 3.841
C29: 5. click on account maintainence | D29: account maintaience page loading time | E29: 45744 | F29: 45744 | G29: 45748 | H29: 45748 | I29: Passed | L29: 2402 | M29: 4.231 | N29: 4.456 | O29: 4.231 | P29: 4.456
C30: 6. select customerid | D30: Loading customerid page | E30: 45744 | F30: 45744 | G30: 45748 | H30: 45748 | I30: Passed | L30: 2401 | M30: 0.509 | N30: 0.573 | O30: 0.509 | P30: 0.573
C31: 7. enterPPIN and SSiN and click on next | D31: submitting PPIN and SSIN | E31: 45744 | F31: 45744 | G31: 45748 | H31: 45748 | I31: Passed | L31: 2400 | M31: 3.85 | N31: 4.112 | O31: 3.85 | P31: 4.112
B32: Account Maintainence(Business acc-customerid | C32: 1. Login to salesforce | E32: 45744 | F32: 45744 | G32: 45748 | H32: 45748 | I32: Passed | Q32: Open Known Risk: https://jira.nexteraenergy.com/browse/SFAD-1363 Defect: https://jira.nexteraenergy.com/browse/SFAD-2104 we will retest this issue along with Field Testing, hence passing this test case conditionally, Results confluence Page: https://confluence.nexteraenergy.com/display/FPLS/Performance+Testing+Results+for+Unified+CRM+Project | R32: Acc_main_business_customerid
C33: 2.homepage | E33: 45744 | F33: 45744 | G33: 45748 | H33: 45748 | I33: Passed
C34: 3.Search AccountNumber | D34: Search with account number | E34: 45744 | F34: 45744 | G34: 45748 | H34: 45748 | I34: Passed | L34: 2424 | M34: 0.234 | N34: 0.242 | O34: 0.234 | P34: 0.242
C35: 4.account dashboard | D35: Laoding account dashboard page | E35: 45744 | F35: 45744 | G35: 45748 | H35: 45748 | I35: Passed | L35: 2423 | M35: 6.921 | N35: 7.781 | O35: 3.587 | P35: 3.841
C36: 5. click on account maintainence | D36: account maintaience page loading time | E36: 45744 | F36: 45744 | G36: 45748 | H36: 45748 | I36: Passed | L36: 2400 | M36: 3.887 | N36: 4.206 | O36: 3.887 | P36: 4.206
C37: 6. select customerid | D37: Loading customerid page | E37: 45744 | F37: 45744 | G37: 45748 | H37: 45748 | I37: Passed | L37: 2400 | M37: 0.486 | N37: 0.481 | O37: 0.486 | P37: 0.481
C38: 7. enter taxid and next | D38: submitting Taxid page | E38: 45744 | F38: 45744 | G38: 45748 | H38: 45748 | I38: Passed | L38: 2400 | M38: 2.436 | N38: 2.679 | O38: 2.436 | P38: 2.679
B39: Account Maintainence(mailing address) | C39: 1. Login to salesforce | E39: 45744 | F39: 45744 | G39: 45749 | H39: 45749 | I39: Passed | Q39: Open Known Risk: https://jira.nexteraenergy.com/browse/SFAD-1363 Defect: https://jira.nexteraenergy.com/browse/SFAD-2104 we will retest this issue along with Field Testing, hence passing this test case conditionally, | R39: Acc_Main_mailingaddress
C40: 2.homepage | E40: 45744 | F40: 45744 | G40: 45749 | H40: 45749 | I40: Passed
C41: 3.Search AccountNumber | D41: Search with account number | E41: 45744 | F41: 45744 | G41: 45749 | H41: 45749 | I41: Passed | L41: 2401 | M41: 0.316 | N41: 0.273 | O41: 0.316 | P41: 0.273
C42: 4.account dashboard | D42: Laoding account dashboard page | E42: 45744 | F42: 45744 | G42: 45749 | H42: 45749 | I42: Passed | L42: 2400 | M42: 7.309 | N42: 7.834 | O42: 3.587 | P42: 3.841
C43: 5. click on account maintainence | D43: account maintaience page loading time | E43: 45744 | F43: 45744 | G43: 45749 | H43: 45749 | I43: Passed | L43: 2400 | M43: 4.243 | N43: 4.435 | O43: 4.243 | P43: 4.435
C44: 6.select mailing address | D44: Loading mailing address page | E44: 45744 | F44: 45744 | G44: 45749 | H44: 45749 | I44: Passed | L44: 2399 | M44: 1.39 | N44: 1.57 | O44: 1.39 | P44: 1.57
C45: 7. enter new adress and next | D45: submitting new address page | E45: 45744 | F45: 45744 | G45: 45749 | H45: 45749 | I45: Passed | L45: 2399 | M45: 4.599 | N45: 5.108 | O45: 4.599 | P45: 5.108
B46: Moveout | C46: 1. Login to salesforce | E46: 45744 | F46: 45744 | G46: 45754 | H46: 45754 | I46: Passed | Q46: Open Known Risk: https://jira.nexteraenergy.com/browse/SFAD-1363 Defect: https://jira.nexteraenergy.com/browse/SFAD-2104 we will retest this issue along with Field Testing, hence passing this test case conditionally, | R46: Moveout
C47: 2. Homepage | E47: 45744 | F47: 45744 | G47: 45754 | H47: 45754 | I47: Passed
C48: 3. search accountnumber | D48: Search with account number | E48: 45744 | F48: 45744 | G48: 45754 | H48: 45754 | I48: Passed | L48: 2419 | M48: 0.217 | N48: 0.243 | O48: 0.217 | P48: 0.243
C49: 4. account dashboard | D49: Laoding account dashboard page | E49: 45744 | F49: 45744 | G49: 45754 | H49: 45754 | I49: Passed | L49: 2419 | M49: 6.725 | N49: 7.184 | O49: 3.587 | P49: 3.841
C50: 5.click on moveout | D50: Moeout loading page | E50: 45744 | F50: 45744 | G50: 45754 | H50: 45754 | I50: Passed | L50: 2409 | M50: 1.806 | N50: 2.023 | O50: 1.806 | P50: 2.023
C51: 6. select contract account | D51: Selecting contract account page | E51: 45744 | F51: 45744 | G51: 45754 | H51: 45754 | I51: Passed | L51: 2401 | M51: 0.919 | N51: 1.113 | O51: 0.919 | P51: 1.113
C52: 7. click on next | D52: click on next | E52: 45744 | F52: 45744 | G52: 45754 | H52: 45754 | I52: Passed | L52: 2401 | M52: 0.391 | N52: 0.439 | O52: 0.391 | P52: 0.439
C53: 8. submit moveout | D53: Submitting moveout page | E53: 45744 | F53: 45744 | G53: 45754 | H53: 45754 | I53: Passed | L53: 2401 | M53: 3.668 | N53: 5.217 | O53: 3.668 | P53: 5.217
B54: Programs(ebill) | C54: 1. Login to salesforce | E54: 45744 | F54: 45744 | G54: 45744 | H54: 45744 | I54: Passed | Q54: Open Known Risk: https://jira.nexteraenergy.com/browse/SFAD-1363 Defect: https://jira.nexteraenergy.com/browse/SFAD-2104 we will retest this issue along with Field Testing, hence passing this test case conditionally, | R54: ebill
C55: 2. Homepage | E55: 45744 | F55: 45744 | G55: 45744 | H55: 45744 | I55: Passed
C56: 3. search accountnumber | D56: Search with account number | E56: 45744 | F56: 45744 | G56: 45744 | H56: 45744 | I56: Passed | L56: 2372 | M56: 0.185 | N56: 0.213 | O56: 0.185 | P56: 0.213
C57: 4. account dashboard | D57: Laoding account dashboard page | E57: 45744 | F57: 45744 | G57: 45744 | H57: 45744 | I57: Passed | L57: 2368 | M57: 6.154 | N57: 6.936 | O57: 3.587 | P57: 3.841
C58: 5. ebill enroll | D58: enbill enroll response time | E58: 45744 | F58: 45744 | G58: 45744 | H58: 45744 | I58: Passed | L58: 2352 | M58: 2.866 | N58: 3.816 | O58: 2.866 | P58: 3.816
C59: 6.ebill update | D59: ebill update response time | E59: 45744 | F59: 45744 | G59: 45744 | H59: 45744 | I59: Passed | L59: 2337 | M59: 1.68 | N59: 1.967 | O59: 1.68 | P59: 1.967
C60: 7.ebill not received | D60: ebill not received response time | E60: 45744 | F60: 45744 | G60: 45744 | H60: 45744 | I60: Passed | L60: 2332 | M60: 1.206 | N60: 1.385 | O60: 1.206 | P60: 1.385
C61: 8.ebill discontinue | D61: ebill discontinue response time | E61: 45744 | F61: 45744 | G61: 45744 | H61: 45744 | I61: Passed | L61: 2328 | M61: 1.826 | N61: 2.149 | O61: 1.826 | P61: 2.149
B62: Programs(budgetbill) | C62: 1. Login to salesforce | E62: 45744 | F62: 45744 | G62: 45753 | H62: 45753 | I62: Passed | Q62: Open Known Risk: https://jira.nexteraenergy.com/browse/SFAD-1363, we will retest this issue along with Field Testing, hence passing this test case conditionally, Defect: https://jira.nexteraenergy.com/browse/SFAD-2104 | R62: Budget Bill
C63: 2. Homepage | E63: 45744 | F63: 45744 | G63: 45753 | H63: 45753 | I63: Passed
C64: 3. search accountnumber | D64: Search with account number | E64: 45744 | F64: 45744 | G64: 45753 | H64: 45753 | I64: Passed | L64: 2400 | M64: 0.201 | N64: 0.231 | O64: 0.201 | P64: 0.231
C65: 4. account dashboard | D65: Laoding account dashboard page | E65: 45744 | F65: 45744 | G65: 45753 | H65: 45753 | I65: Passed | L65: 2400 | M65: 6.144 | N65: 6.619 | O65: 3.587 | P65: 3.841
C66: 5. Click on enroll | D66: click on enroll page | E66: 45744 | F66: 45744 | G66: 45753 | H66: 45753 | I66: Passed | L66: 2400 | M66: 3.014 | N66: 3.269 | O66: 3.014 | P66: 3.269
C67: 6. Submit enroll | D67: submit enroll page | E67: 45744 | F67: 45744 | G67: 45753 | H67: 45753 | I67: Passed | L67: 2400 | M67: 1.608 | N67: 2.386 | O67: 1.608 | P67: 2.386
C68: 7. click on discotinue | D68: click on discontinue page | E68: 45744 | F68: 45744 | G68: 45753 | H68: 45753 | I68: Passed | L68: 2400 | M68: 3.752 | N68: 4.291 | O68: 3.752 | P68: 4.291
C69: 8. discontinue BB | D69: discontinue BB | E69: 45744 | F69: 45744 | G69: 45753 | H69: 45753 | I69: Passed | L69: 2400 | M69: 1.312 | N69: 1.588 | O69: 1.312 | P69: 1.588
B70: Programs(ABP) | C70: 1. Login to salesforce | E70: 45744 | F70: 45744 | G70: 45753 | H70: 45753 | I70: Passed | Q70: Open Known Risk: https://jira.nexteraenergy.com/browse/SFAD-1363, we will retest this issue along with Field Testing, hence passing this test case conditionally, Defect: https://jira.nexteraenergy.com/browse/SFAD-2104 | R70: ABP
C71: 2. Homepage | E71: 45744 | F71: 45744 | G71: 45753 | H71: 45753 | I71: Passed
C72: 3. search accountnumber | D72: Search with account number | E72: 45744 | F72: 45744 | G72: 45753 | H72: 45753 | I72: Passed | L72: 2403 | M72: 0.193 | N72: 0.226 | O72: 0.193 | P72: 0.226
C73: 4. account dashboard | D73: Laoding account dashboard page | E73: 45744 | F73: 45744 | G73: 45753 | H73: 45753 | I73: Passed | L73: 2403 | M73: 6.103 | N73: 6.638 | O73: 3.587 | P73: 3.841
C74: 5. click on update | D74: Click on update page | E74: 45744 | F74: 45744 | G74: 45753 | H74: 45753 | I74: Passed | L74: 2403 | M74: 3.441 | N74: 3.74 | O74: 3.441 | P74: 3.74
C75: 6. ABP update | D75: ABP update response time | E75: 45744 | F75: 45744 | G75: 45753 | H75: 45753 | I75: Passed | L75: 2401 | M75: 0.446 | N75: 0.512 | O75: 0.446 | P75: 0.512
C76: 7. Click on pause | D76: ABP discontinue response time | E76: 45744 | F76: 45744 | G76: 45753 | H76: 45753 | I76: Passed | L76: 2400 | M76: 3.458 | N76: 3.734 | O76: 3.458 | P76: 3.734
C77: 8. submit pause | D77: submit pause page | E77: 45744 | F77: 45744 | G77: 45753 | H77: 45753 | I77: Passed | L77: 2393 | M77: 1.597 | N77: 1.802 | O77: 1.597 | P77: 1.802
C78: 9. click on discontinue | D78: clickon discotinue | E78: 45744 | F78: 45744 | G78: 45753 | H78: 45753 | I78: Passed | L78: 2389 | M78: 2.606 | N78: 2.806 | O78: 2.606 | P78: 2.806
C79: 10. Discontinue ABP | D79: discontinue ABP | E79: 45744 | F79: 45744 | G79: 45753 | H79: 45753 | I79: Passed | L79: 2387 | M79: 1.574 | N79: 1.775 | O79: 1.574 | P79: 1.775
B81: Account Dashboard | C81: Search Account Number | D81: Search Account Number | E81: 45760 | F81: 45760 | G81: 45760 | H81: 45760 | I81: Passed | L81: 2426 | M81: 0.223 | N81: 0.244 | R81: https://nee.sharepoint.com/teams/EXT_CIStoSAP/Shared%20Documents/Forms/AllItems.aspx?id=%2Fteams%2FEXT%5FCIStoSAP%2FShared%20Documents%2FOperational%20Readiness%20and%20Testing%2F00%2E%20Integrated%20Releases%2F01%2D%20Integrated%20Release%201%2E0%2F02%2E%20UAT%2F03%2E%20Performance%20Testing%2FUnified%20CRM%2D%20Performance%20Test%2FEmployee%20desktop&viewid=7c6b97d2%2De29a%2D4b27%2D98e7%2D3f5d5bd11dff&CT=1744734421771&OR=OWA%2DNT%2DMail&CID=fdad4da5%2D3ad1%2D9d3f%2Ddbc8%2Ddc1163ee8893&e=5%3A114072a8299643868b1c4fc0e1a4594b&sharingv2=true&fromShare=true&at=9&FolderCTID=0x012000D735ADCC1E28D24684C83D05ABBC84C7
C82: Account 360 | D82: Account 360 | E82: 45760 | F82: 45760 | G82: 45760 | H82: 45760 | I82: Passed | L82: 2426 | M82: 3.587 | N82: 3.841
B84: Fixed Rate | C84: Search Account Number | D84: Search Account Number | E84: 45893 | F84: 45893 | G84: 45901 | H84: 45901 | I84: pass | L84: 2500 | M84: 0.163 | N84: 0.228 | O84: 0.153 | P84: 0.221
C85: Account 360 | D85: Account 360 | E85: 45893 | F85: 45893 | G85: 45901 | H85: 45901 | I85: Pass | L85: 2500 | M85: 3.72 | N85: 6.76 | O85: 3.363 | P85: 5.815
C86: Click on enroll | D86: Click on enroll | E86: 45893 | F86: 45893 | G86: 45901 | H86: 45901 | I86: Pass | J86: SFAD-6090 | L86: 2500 | M86: 33.534 | N86: 33.534 | O86: 2.472 | P86: 4.204
C87: Enroll fixed rate | D87: Enroll fixed rate | E87: 45893 | F87: 45893 | G87: 45901 | H87: 45901 | I87: Pass | L87: 2490 | O87: 2.397 | P87: 2.776
C88: Click on discontinue | D88: Click on discontinue | E88: 45893 | F88: 45893 | G88: 45901 | H88: 45901 | I88: Pass | L88: 2490 | O88: 3.897 | P88: 4.103
C89: discontiue fixed rate | D89: discontiue fixed rate | E89: 45893 | F89: 45893 | G89: 45901 | H89: 45901 | I89: Pass | L89: 2490 | O89: 2.542 | P89: 3.066
A91: IR3.1 | B91: Account 360 | C91: 1. Login to salesforce | E91: 46073 | F91: 46073 | I91: Pass | L91: 2500 | M91: 0.68 | N91: 0.705
C92: 2. Homepage | E92: 46073 | F92: 46073 | I92: Pass | L92: 2500 | M92: 0.588 | N92: 0.684
C93: 3. Search account Number | D93: Search account Number | E93: 46073 | F93: 46073 | I93: Pass | L93: 2500 | M93: 0.243 | N93: 0.276
C94: 4. Account 360 page | D94: Account 360 page | E94: 46073 | F94: 46073 | I94: Failed | J94: https://jira.nexteraenergy.com/browse/CRAID-2844 | L94: 2500 | M94: 23.458 | N94: 32.478
B96: Premise 360 | C96: 1. Login to salesforce | E96: 46073 | F96: 46073 | I96: Pass | L96: 2500 | M96: 0.68 | N96: 0.705
C97: 2. Homepage | E97: 46073 | F97: 46073 | I97: Pass | L97: 2500 | M97: 0.588 | N97: 0.684
C98: 3. Search premise Number | D98: Search premise Number | E98: 46073 | F98: 46073 | I98: Pass | L98: 2500 | M98: 0.255 | N98: 0.298
C99: 4. premise 360 page | D99: premise 360 page | E99: 46073 | F99: 46073 | I99: Failed | J99: https://jira.nexteraenergy.com/browse/CRAID-2844 | L99: 2500 | M99: 22.88 | N99: 48.493
B101: Customer 360 | C101: 1. Login to salesforce | E101: 46073 | F101: 46073 | I101: Pass | L101: 2500 | M101: 0.68 | N101: 0.705
C102: 2. Homepage | E102: 46073 | F102: 46073 | I102: Pass | L102: 2500 | M102: 0.588 | N102: 0.684
C103: 3. Search customer Number | D103: Search customer Number | E103: 46073 | F103: 46073 | I103: Pass | L103: 2500 | M103: 0.164 | N103: 0.196
C104: 4. Customer 360 page | D104: Customer 360 page | E104: 46073 | F104: 46073 | I104: Failed | J104: https://jira.nexteraenergy.com/browse/CRAID-2844 | L104: 2500 | M104: 14.13 | N104: 27.719
B106: Account 360 | C106: Mix of all 360's | D106: Account 360 | E106: 46073 | F106: 46073 | I106: Failed | L106: 500 each type total 1500 | M106: 18.271 | N106: 31.351
...

Sheet Reporting & Analytics
A1: Performance Testing Scenarios | B1: Functional Steps | C1: Planned Execution Date | D1: Execution Status | E1: Performance Test Lead

Sheet SAP
A1: Performance Testing Scenarios | B1: Functional Steps | C1: Planned Execution Date | D1: Execution Status | E1: Performance Test Lead

Sheet SAP - Basis
A1: Performance Testing Scenarios | B1: Functional Steps | C1: Planned Execution Date | D1: Execution Status | E1: Performance Test Lead

Sheet Tax
A1: Performance Testing Scenarios | B1: Functional Steps | C1: Planned Execution Date | D1: Execution Status | E1: Performance Test Lead

Sheet Telephony
J1: Legacy Standard | N1: FPL NW Standard | R1: Industry Standard
A2: Performance Testing Scenarios | B2: Functional Steps | C2: Planned Execution Date | D2: Execution Status | E2: No.of requests | F2: Avg response time(ms) | G2: 90%Line (ms) | H2: Performance Test Lead | I2: Test Cases | J2: Legacy Application | K2: User/Data Load Volumetrics | L2: Average Response Time | M2: 90% Line | N2: FPL NW Application | O2: User/Data Load Volumetrics | P2: Average Response Time | Q2: 90% Line | R2: Average Response Time | S2: 90% Line | T2: Reasons for Deviations | U2: How 90% Line is calculated for Current Performance Test
A3: Agent Transfer - No Match No Input | B3: Dial the FPL customer service number. Tester to call from a phone number which is not present in the FPL database and results in No ANI Match | C3: 45768 | D3: Not Run | H3: Vish | I3: XDX-TC-18986
B4: System prompt Emergency situation message | C4: 45768 | D4: Not Run
B5: System prompt disambigitue 1 HVCA No input match | C5: 45768 | D5: Not Run
B6: System prompt No match auth HVCA | C6: 45768 | D6: Not Run
B7: prompt to transition to Auth | C7: 45768 | D7: Not Run
B8: system prompt for googbye_no_ani | C8: 45768 | D8: Not Run
B9: Customer end the call | C9: 45768 | D9: Not Run
A10: Agent Transfer - Police/Fire with PIN | B10: Police/Fire/Publix dials outage toll free number (NW + Legacy Number): 833-919-0943. Tester to call from a phone number which is not present in the FPL database and results in No ANI Match | C10: 45768 | D10: Not Run | H10: Vish | I10: XDX-TC-19565
B11: IVR plays prompt to caller | C11: 45768 | D11: Not Run
B12: Caller enters PIN (777 or 711) | C12: 45768 | D12: Not Run
B13: System check the trunk availablity | C13: 45768 | D13: Not Run
B14: IVR plays agent transfer message | C14: 45768 | D14: Not Run
A15: Agent Trasnfer - No ANI Match Authentication with Phone number | B15: Dial the FPL customer service number. | C15: 45768 | D15: Not Run | H15: Vish | I15: XDX-TC-18955
B16: System prompt Emergency situation message | C16: 45768 | D16: Not Run
B17: System prompt for menu option since after no ani match occurred. | C17: 45768 | D17: Not Run
B18: System prompt to verify address | C18: 45768 | D18: Not Run
B19: system gives option to use their phone number or account number to verify | C19: 45768 | D19: Not Run
B20: User gives a phone number that doesnt match an account | C20: 45768 | D20: Not Run
B21: system tells user that number didnt match | C21: 45768 | D21: Not Run
B22: System tells user to call back and conversation ends | C22: 45768 | D22: Not Run
B23: Call ends after user disconnects the call | C23: 45768 | D23: Not Run
A24: Agent Transfer - Report DownWire | B24: Legacy Residential customer dials outage toll free number (NW + Legacy Number): 833-919-0943 | C24: 45768 | D24: Not Run | H24: Vish | I24: XDX-TC-19499
B25: Customer says "Yes" to confirm the address | C25: 45768 | D25: Not Run
B26: Customer says "No" | C26: 45768 | D26: Not Run
B27: Customer says "Downed wire" | C27: 45768 | D27: Not Run
B28: IVR confirms trunk availability | C28: 45768 | D28: Not Run
B29: Call is connected with an agent | C29: 45768 | D29: Not Run

Sheet Web Optimization & Mobile
L1: Legacy Standard | P1: FPL NW Standard | T1: Industry Standard
B2: Performance Testing Scenarios | C2: Functional Steps | D2: No.of requests | E2: Avg response time(s) | F2: 90%Line (s) | G2: Planned Execution Date | H2: Execution Status | I2: Performance Test Lead | J2: Test Result | K2: Remarks/ Additional Details | L2: Legacy Application | M2: User/Data Load Volumetrics | N2: Average Response Time | O2: 90% Line | P2: FPL NW Application | Q2: User/Data Load Volumetrics | R2: Average Response Time | S2: 90% Line | T2: Average Response Time | U2: 90% Line | V2: Reasons for Deviations | W2: How 90% Line is calculated for Current Performance Test
B3: Ebill Phase2 | C3: Login to webqa.fpl.com | I3: Saswat Ranjan Sahoo | J3: Ebill Phase 2 | L3: N/A | N3: N/A Useful reference, but we use the stricter 90% line for our SLAs. | O3: ~3s | P3: N/A | R3: N/A Useful reference, but we use the stricter 90% line for our SLAs. | S3: ~3s | T3: Average is useful, but is not as strict as 90% line. It allows for large deviations and diminishes their impact when averaged out with fast responses. Web focuses on 90% line since that metric will truly tell us how many transactions are past SLA. | U3: Marketing & Communications provide this SLA for FPL.COM. 40% of users will leave a website if it takes more than 3 seconds to load. Aiming for a page load time under 3 seconds is crucial for a positive user experience and can even impact search engine rankings. | W3: 90% Line is the maximum amount of time under which 90% of transactions have been completed. Think of it in reverse: 10% of transactions come back over this value.
C4: Ebill Eligiblity | D4: 3474 | E4: 0.2 | F4: 0.22 | G4: 45754 | H4: Passed | M4: 2072 | Q4: 301
C5: Click on Ebill enrollment | D5: 3474 | E5: 2.47 | F5: 3.01 | G5: 45754 | H5: Passed
C6: Click on Ebill Edit | D6: 3446 | E6: 0.81 | F6: 0.97 | G6: 45754 | H6: Passed
C7: Click on Ebill discontinue | D7: 3440 | E7: 0.99 | F7: 1.16 | G7: 45754 | H7: Passed
B8: Budget Bill | C8: Budget bill Eligibility | D8: 400 | E8: 1.45 | F8: 1.95 | G8: 45755 | H8: Passed | I8: Saswat Ranjan Sahoo | J8: Budget Bill | M8: 181 | Q8: 60
C9: Click on Budget bill enrollment | D9: 400 | E9: 1.18 | F9: 1.78 | G9: 45755 | H9: Passed
C10: Click on Budget bill discontinue | D10: 400 | E10: 0.3 | F10: 0.56 | G10: 45755 | H10: Passed
B11: Account Maintenance | C11: Update Phone | D11: 3346 | E11: 2.69 | F11: 4.38 | G11: 45755 | H11: Passed | I11: Ankita Barik | J11: Account Settings | M11: N/A | Q11: N/A | V11: Deeper analysis to the individual hops this transaction makes reveals that the reason this number is high is exclusively due to a call to Preferences (MongoDB) which was not part of the IR1.0 deliverables. Our FPL Architect has decided this can be left as is since there is already a project underway to migrate MongoDB Preferences to UCDP, and will require a performance pass in the near future regardless. UCPD + Mulesoft architects are included and aware of this information. You can review this email thread here.
C12: Update Email | D12: 3379 | E12: 1.55 | F12: 1.05 | G12: 45755 | H12: Passed
C13: Update Mailing Address | D13: 3374 | E13: 0.13 | F13: 0.17 | G13: 45755 | H13: Passed
B14: Move out | C14: Dashboard | D14: 3000 | E14: 0.68 | F14: 1.03 | G14: 45763 | H14: Passed | I14: Chilamakurthi, Yuva sai sri Saswat Ranjan Sahoo | J14: Start, Stop and Mover services | M14: 140 | Q14: 40
C15: Start service view details | D15: 1000 | E15: 0.24 | F15: 0.32 | G15: 45763 | H15: Passed
C16: Start service edit | D16: 1000 | E16: 0.83 | F16: 0.95 | G16: 45763 | H16: Passed
C17: Stop service view details | D17: 1000 | E17: 0.24 | F17: 0.32 | G17: 45763 | H17: Passed
C18: Stop service edit | D18: 1000 | E18: 0.83 | F18: 0.95 | G18: 45763 | H18: Passed
C19: Move service move from view details | D19: 1000 | E19: 0.23 | F19: 0.31 | G19: 45763 | H19: Passed
C20: Move service move from edit | D20: 1000 | E20: 0.82 | F20: 0.91 | G20: 45763 | H20: Passed
C21: Move service move to view details | D21: 1000 | E21: 0.24 | F21: 0.3 | G21: 45763 | H21: Passed
C22: Move serve move to edit | D22: 1000 | E22: 0.81 | F22: 0.93 | G22: 45763 | H22: Passed
C23: communication info | D23: 3000 | E23: 0.76 | F23: 0.82 | G23: 45763 | H23: Passed | J23: Moveout | M23: 140 | Q23: 40
C24: Installation | D24: 3000 | E24: 0.15 | F24: 0.16 | G24: 45763 | H24: Passed
C25: Disconnect date validate | D25: 3000 | E25: 0.29 | F25: 0.36 | G25: 45763 | H25: Passed
C26: Region Type | D26: 2994 | E26: 0.07 | F26: 0.08 | G26: 45763 | H26: Passed
C27: Mailing Address Validate | D27: 2994 | E27: 0.13 | F27: 0.14 | G27: 45763 | H27: Passed
C28: Submit Disconnect | D28: 2994 | E28: 2.71 | F28: 2.91 | G28: 45763 | H28: Passed
B29: ABP Phase 1 | C29: ABP Eligiblity | D29: 400 | E29: 0.14 | F29: 0.16 | G29: 45847 | H29: Passed | I29: Saswat Ranjan Sahoo | J29: ABP Phase 1 | L29: NA | M29: 205 | Q29: 31
C30: ABP Enrollment | D30: 400 | E30: 0.83 | F30: 0.91 | G30: 45847 | H30: Passed
C31: ABP Pause program | D31: 400 | E31: 0.77 | F31: 0.84 | G31: 45847 | H31: Passed
C32: ABP Resume program | D32: 400 | E32: 0.81 | F32: 0.89 | G32: 45847 | H32: Passed
C33: ABP Discontinue | D33: 400 | E33: 0.77 | F33: 0.84 | G33: 45847 | H33: Passed
A34: IR3.1 | B34: Account Summary | C34: Business Card | D34: 1362 | E34: 1.96 | F34: 4.79 | G34: 46084 | H34: Passed | I34: Siva Kannan | J34: Account Summary | M34: N/A | P34: Yes | Q34: 20
B35: Multi Disconnect | C35: List | D35: 200 | E35: 5.07 | F35: 8.37 | G35: 46077 | H35: Passed | I35: Saswat Ranjan Sahoo | J35: Multi Disconnect | K35: NA | L35: NA | M35: 50 | O35: NA | P35: Yes | Q35: 50
C36: Account-Info | D36: 200 | E36: 8.55 | F36: 10.1 | G36: 46077 | H36: Passed
C37: Validate-date | D37: 200 | E37: 8.66 | F37: 13.8 | G37: 46077 | H37: Passed
C38: Mailing Address Validate | D38: 200 | E38: 0.23 | F38: 0.27 | G38: 46077 | H38: Passed
C39: Submit Disconnect | D39: 200 | E39: 0.26 | F39: 0.33 | G39: 46077 | H39: Passed
B40: Account Summary | C40: Account Summary | D40: 4700 | E40: 1.02 | F40: 1.66 | G40: 46087 | H40: In Progress | I40: Saswat Ranjan Sahoo | J40: Account Summary | K40: NA | L40: Account Summary | M40: 150 | P40: Yes | Q40: 50

Sheet Execution Status
A1: Blocked
A2: Failed
A3: In Progress
A4: Not Applicable
A5: Not Executed
A6: Not Run
A7: Passed
A8: Retest

Sheet Performance Testing Report View
A1: Workstream | B1: Total Scenarios | C1: Total Excluding N/A | D1: Plan to Week | E1: Executed Scenarios | F1: Passed Scenarios | G1: Planned Remaining | H1: Plan Week % Complete | I1: Total Remaining | J1: Execution % | K1: Pass Rate % | L1: Business KPI | M1: Performance Requirements | N1: How load is determined
A2: Architecture (UCDP) | B2: 6 | C2: 6 | D2: 6 | E2: 6 | F2: 6 | G2: 0 | H2: 1 | I2: =B2-E2 -> 0 | J2: =E2/B2*100 -> 100 | K2: =F2/E2*100 -> 100 | L2: - Realtime ingestion of interactions from the channels - Sub-second interactions retrievals | M2: - System should be capable of handling 1 million reads & 1 million writes in parallel for a duration of 1 hour - System should not be exceeding response times of 100ms under peak-load scenarios | N2: - Did volume analysis of existing CCINs for NW + Legacy customers, which came to ~300 million interactions in a month - Understood from business the peak load scenarios - Multiplied the peak load scenario number by 10x to achieve a much higher throughput - Stress tested the system with near maximum concurrency to come to a point where the system starts to throttle
A3: Case Management | B3: =COUNTA('Case Management'!B3:B86) -> 9 | C3: 6 | D3: 6 | E3: 6 | F3: 6 | G3: 0 | H3: 1 | I3: =B3-E3 -> 3 | J3: =E3/B3*100 -> 66.666667 | K3: =F3/E3*100 -> 100 | L3: Average Response time,90% Line, % errors | M3: API's should not be exceeding 5 sec under peak load scenarios | N3: volume details understood from business peak load scenarios it is around ~300 so 10x to achieve transactions per hour
A4: CS Field Service | B4: =COUNTA('CS Field Service'!B3:B58) -> 8 | C4: 5 | D4: 5 | E4: 5 | F4: 5 | G4: 0 | H4: 1 | I4: =B4-E4 -> 3 | J4: =E4/B4*100 -> 62.5 | K4: =F4/E4*100 -> 100 | L4: Average Response time,90% Line, % errors | M4: API's should not be exceeding 5 sec under peak load scenarios | N4: volume details understood from business peak load scenarios it is around ~9 so 10x to achieve transactions per hour, Discussed with Business(Urquiaga, Alejandro), @Steven Licari provided load details and we used the same multiplied by 10X
A5: Employee Desktop | B5: 9 | C5: 9 | D5: 9 | E5: 9 | F5: 9 | G5: 0 | H5: 1 | I5: =B5-E5 -> 0 | J5: =E5/B5*100 -> 100 | K5: =F5/E5*100 -> 100 | L5: Average Response time,90% Line, % errors | M5: API's should not be exceeding 5 sec under peak load scenarios | N5: volume details understood from business peak load scenarios it is around ~1000 so 10x to achieve transactions per hour, Discussed with Business Castro, Jaime, & Vargas, Ricardo, with provided load details and we used the same multiplied by 10X
A6: Integrations & Mulesoft | B6: =COUNTA('Integrations Mulesfot'!A3:A106) -> 5 | C6: 5 | D6: 5 | E6: 5 | F6: 5 | G6: 0 | H6: 1 | I6: =B6-E6 -> 0 | J6: =E6/B6*100 -> 100 | K6: =F6/E6*100 -> 100 | L6: Average Response time,90% Line, % errors | M6: On an average, it should not take more than 5 Sec | N6: Determined from Unified CRM scenarios
A7: Web Optimization & Mobile | B7: =COUNTA('Web Optimization & Mobile'!B3:B84) -> 8 | C7: 4 | D7: 4 | E7: 4 | F7: 4 | G7: 0 | H7: 1 | I7: =B7-E7 -> 4 | J7: =E7/B7*100 -> 50 | K7: =F7/E7*100 -> 100 | L7: Average Respnse time,90% Line, % errors | M7: 90% of calls should not exceed 3 sec under peak load, target <5% errors | N7: Max traffic seen on site for Legacy + NW customers according to Adobe Analytics + 10% accounting for growth
A8: Total | B8: =SUM(B2:B7) -> 45 | C8: =SUM(C2:C7) -> 35 | D8: =SUM(D2:D7) -> 35 | E8: =SUM(E2:E7) -> 35 | F8: =SUM(F2:F7) -> 35 | G8: 0 | H8: 1 | I8: =B8-E8 -> 10 | J8: =E8/B8*100 -> 77.777778 | K8: =F8/E8*100 -> 100
A12: Planned By Week
A13: Workstream | B13: Week 1 (03/10/2025-03/14/2025) | C13: Week 2 (03/17/2025-03/21/2025) | D13: Week 3 (03/24/2025-03/28/2025) | E13: Week 4 (03/31/2025-04/04/2025) | F13: Week 5 (04/07/2025-04/10/2025)
A14: Architecture (UCDP) | B14: 6
A15: Case Management | C15: 6
A16: CS Field Service | E16: 3 | F16: 2
A17: Employee Desktop | E17: 7 | F17: 2
A18: Integrations & Mulesoft | B18: 5
A19: Telephony
A20: Web Optimization & Mobile | E20: 1 | F20: 3
A21: Total | B21: =SUM(B14:B20) -> 11 | C21: =SUM(C14:C20) -> 6 | D21: =SUM(D14:D20) -> 0 | E21: =SUM(E14:E20) -> 11 | F21: =SUM(F14:F20) -> 7
A23: Workstream | B23: Total Scenarios | C23: Planned Executed Scenarios | D23: Actual Passed Scenarios | E23: Planned Remaining | F23: Plan Week % Complete | H23: Execution % | I23: Pass Rate % | J23: Business KPI | K23: Performance Requirements | L23: How load is determined
A24: Convo AI | B24: 8
A25: Telephony | B25: 4
A28: Workstream | B28: Performance Testing (Yes/No) | C28: If no, why? | D28: Point of Contact | E28: Number of Scenarios for Performance Testing | F28: Total Functional Steps
A29: Architecture (UCDP) | B29: yes | C29: yes | D29: Hussain Gilani/ Tisha Haque | E29: =COUNTA('Architecture (UCDP)'!A78:A176) -> 0 | F29: 50
A30: Case Management | B30: yes | C30: yes | D30: Srividya Chamarthy | E30: =COUNTA('Case Management'!B26:B119) -> 7 | F30: 36
A31: Convo AI (IVR) | B31: yes | C31: yes | D31: Vishwanath Vinnakota | E31: 8 | F31: =COUNTA('Convo AI (IVR)'!B131:B228) -> 42
A32: CS Field Service | B32: yes | C32: yes | D32: Srividya Chamarthy | E32: =COUNTA('CS Field Service'!B29:B94) -> 11 | F32: =COUNTA('CS Field Service'!C29:C94) -> 39
A33: DCP Customer communications | B33: No | C33: Not part of IR1.0 | D33: No | E33: N/A | F33: N/A
A34: Employee Desktop | B34: yes | C34: yes | D34: Srividya Chamarthy | E34: =COUNTA('Employee Desktop'!B33:B126) -> 13 | F34: =COUNTA('Employee Desktop'!C33:C127) -> 68
A35: Integrations & Mulesoft | B35: yes | C35: yes | D35: Ramesh Reddy Kota | E35: 5 | F35: =COUNTA('Integrations Mulesfot'!B35:B139) -> 0
A36: Reporting & Analytics | B36: No | C36: Only 9 test cases and nothing for performance test | D36: No | E36: N/A | F36: N/A
A37: SAP - Billing & Payment (BPO) | B37: No | C37: No changes in IR1 that require performance testing. Some are planned for later releases | D37: N/A | E37: N/A | F37: N/A
A38: SAP - Revenue Recovery | B38: N/A | C38: N/A | D38: N/A | E38: N/A | F38: N/A
A39: SAP - Basis | B39: No | C39: Only offcycle performance test to validate solution for DEE | D39: No | E39: N/A | F39: N/A
A40: SAP- Tax | B40: No | C40: Waiting to install Vertex. Not available for IR 1.0 | D40: No | E40: N/A | F40: N/A
A41: Telephony | B41: yes | C41: yes | D41: Vishwanath Vinnakota | E41: 4 | F41: 27
A42: Web Optimization & Mobile | B42: yes | C42: yes | D42: Saswat Ranjan Sahoo | E42: =COUNTA(Telephony!A37:A153) -> 0 | F42: =COUNTA(Telephony!B37:B126) -> 0

Sheet Action Items
A2: Workstream | B2: Performance Testing Scenarios | C2: Functional Steps | D2: Execution Status | E2: No.of requests | F2: Avg response time(s) | G2: 90%Line | H2: Rerun avg Response time for account 360 page with 2401 requestd | I2: Rerun 90%Line for account 360 page with 2401 requestd
A3: Field Service | B3: Appointment Booking( worktype as EESA) | C3: Search AccountNumber | D3: Passed | E3: 30 | F3: 0.249 | G3: 0.343
C4: Account Dashboard | D4: Passed | E4: 30 | F4: 7.468 | G4: 7.616 | H4: 3.587 | I4: 3.841
C5: Click on appointment | D5: Passed | E5: 30 | F5: 2.139 | G5: 2.727
C6: Click on worktype EESA_and_Next | D6: Passed | E6: 30 | F6: 6.439 | G6: 9.683
C7: Click on time slot | D7: Passed | E7: 30 | F7: 2.604 | G7: 2.563
C8: Click on submit | D8: Passed | E8: 30 | F8: 7.431 | G8: 12.707
B9: Appointment Booking( worktype as SURV) | C9: Search AccountNumber | D9: Passed | E9: 30 | F9: 0.226 | G9: 0.277
C10: Account Dashboard | D10: Passed | E10: 30 | F10: 8.001 | G10: 7.46 | H10: 3.587 | I10: 3.841
C11: Click on appointment | D11: Passed | E11: 30 | F11: 2.074 | G11: 2.378
C12: Click on worktype SURV | D12: Passed | E12: 30 | F12: 7.561 | G12: 11.679
C13: Click on time slot | D13: Passed | E13: 30 | F13: 2.596 | G13: 2.922
C14: Click on submit | D14: Passed | E14: 30 | F14: 8.236 | G14: 11.108
B15: Appointment Booking( worktype as BEE) | C15: Search AccountNumber | D15: Passed | E15: 30 | F15: 0.229 | G15: 0.3
C16: Account Dashboard | D16: Passed | E16: 30 | F16: 7.61 | G16: 8.756 | H16: 3.587 | I16: 3.841
C17: Click on appointment | D17: Passed | E17: 30 | F17: 2.156 | G17: 2.734
C18: Click on worktype business energy evaluation | D18: Passed | E18: 30 | F18: 7.105 | G18: 9.868
C19: Click on time slot | D19: Passed | E19: 30 | F19: 2.532 | G19: 3.044
C20: Click on submit | D20: Passed | E20: 30 | F20: 6.988 | G20: 8.371
B21: API | C21: Energy Analyzer | D21: Passed | E21: 2000 | F21: 0.789 | G21: 1.301
B22: API | C22: Get Alerts | D22: Passed | E22: 2000 | F22: 0.563 | G22: 0.959
A23: Web Optimization & Mobile | B23: Account Maintenance | C23: Update Phone | D23: Passed | E23: 3346 | F23: 2.69 | G23: 4.38
C24: Update Email | D24: Passed | E24: 3379 | F24: 1.55 | G24: 1.05
C25: Update Mailing Address | D25: Passed | E25: 3374 | F25: 0.13 | G25: 0.17
